{"textAnnotations": [{"locale": "ta", "description": "\u0bae\u0bc1\u0b9f\u0bbf \u0ba4\u0bbf\u0bb0\u0bc1\u0ba4\u0bcd\u0ba4\u0bc1\u0bae\u0bcd\n", "boundingPoly": {"vertices": [{"x": 73, "y": -1}, {"x": 272, "y": -1}, {"x": 272, "y": 35}, {"x": 73, "y": 35}]}}, {"description": "\u0bae\u0bc1\u0b9f\u0bbf", "boundingPoly": {"vertices": [{"x": 73}, {"x": 123}, {"x": 123, "y": 33}, {"x": 73, "y": 33}]}}, {"description": "\u0ba4\u0bbf\u0bb0\u0bc1\u0ba4\u0bcd\u0ba4\u0bc1\u0bae\u0bcd", "boundingPoly": {"vertices": [{"x": 125, "y": -1}, {"x": 272}, {"x": 272, "y": 35}, {"x": 125, "y": 34}]}}], "fullTextAnnotation": {"pages": [{"property": {"detectedLanguages": [{"languageCode": "ta", "confidence": 1.0}]}, "width": 334, "height": 500, "blocks": [{"property": {"detectedLanguages": [{"languageCode": "ta", "confidence": 1.0}]}, "boundingBox": {"vertices": [{"x": 73, "y": -1}, {"x": 272, "y": 1}, {"x": 272, "y": 36}, {"x": 73, "y": 34}]}, "paragraphs": [{"property": {"detectedLanguages": [{"languageCode": "ta", "confidence": 1.0}]}, "boundingBox": {"vertices": [{"x": 73, "y": -1}, {"x": 272, "y": 1}, {"x": 272, "y": 36}, {"x": 73, "y": 34}]}, "words": [{"property": {"detectedLanguages": [{"languageCode": "ta"}]}, "boundingBox": {"vertices": [{"x": 73}, {"x": 123}, {"x": 123, "y": 33}, {"x": 73, "y": 33}]}, "symbols": [{"property": {"detectedLanguages": [{"languageCode": "ta"}]}, "boundingBox": {"vertices": [{"x": 73}, {"x": 99}, {"x": 99, "y": 33}, {"x": 73, "y": 33}]}, "text": "\u0bae"}, {"property": {"detectedLanguages": [{"languageCode": "ta"}]}, "boundingBox": {"vertices": [{"x": 100}, {"x": 105}, {"x": 105, "y": 33}, {"x": 100, "y": 33}]}, "text": "\u0bc1"}, {"property": {"detectedLanguages": [{"languageCode": "ta"}]}, "boundingBox": {"vertices": [{"x": 106}, {"x": 117}, {"x": 117, "y": 33}, {"x": 106, "y": 33}]}, "text": "\u0b9f"}, {"property": {"detectedLanguages": [{"languageCode": "ta"}], "detectedBreak": {"type": "SPACE"}}, "boundingBox": {"vertices": [{"x": 118}, {"x": 123}, {"x": 123, "y": 33}, {"x": 118, "y": 33}]}, "text": "\u0bbf"}]}, {"property": {"detectedLanguages": [{"languageCode": "ta"}]}, "boundingBox": {"vertices": [{"x": 125, "y": -1}, {"x": 272}, {"x": 272, "y": 35}, {"x": 125, "y": 34}]}, "symbols": [{"property": {"detectedLanguages": [{"languageCode": "ta"}]}, "boundingBox": {"vertices": [{"x": 125}, {"x": 159}, {"x": 159, "y": 34}, {"x": 125, "y": 34}]}, "text": "\u0ba4"}, {"property": {"detectedLanguages": [{"languageCode": "ta"}]}, "boundingBox": {"vertices": [{"x": 160}, {"x": 165}, {"x": 165, "y": 34}, {"x": 160, "y": 34}]}, "text": "\u0bbf"}, {"property": {"detectedLanguages": [{"languageCode": "ta"}]}, "boundingBox": {"vertices": [{"x": 166}, {"x": 177}, {"x": 177, "y": 34}, {"x": 166, "y": 34}]}, "text": "\u0bb0"}, {"property": {"detectedLanguages": [{"languageCode": "ta"}]}, "boundingBox": {"vertices": [{"x": 178}, {"x": 183}, {"x": 183, "y": 34}, {"x": 178, "y": 34}]}, "text": "\u0bc1"}, {"property": {"detectedLanguages": [{"languageCode": "ta"}]}, "boundingBox": {"vertices": [{"x": 184}, {"x": 207}, {"x": 207, "y": 34}, {"x": 184, "y": 34}]}, "text": "\u0ba4"}, {"property": {"detectedLanguages": [{"languageCode": "ta"}]}, "boundingBox": {"vertices": [{"x": 208}, {"x": 213}, {"x": 213, "y": 34}, {"x": 208, "y": 34}]}, "text": "\u0bcd"}, {"property": {"detectedLanguages": [{"languageCode": "ta"}]}, "boundingBox": {"vertices": [{"x": 214}, {"x": 225}, {"x": 225, "y": 34}, {"x": 214, "y": 34}]}, "text": "\u0ba4"}, {"property": {"detectedLanguages": [{"languageCode": "ta"}]}, "boundingBox": {"vertices": [{"x": 226}, {"x": 237}, {"x": 237, "y": 34}, {"x": 226, "y": 34}]}, "text": "\u0bc1"}, {"property": {"detectedLanguages": [{"languageCode": "ta"}]}, "boundingBox": {"vertices": [{"x": 238}, {"x": 255}, {"x": 255, "y": 34}, {"x": 238, "y": 34}]}, "text": "\u0bae"}, {"property": {"detectedLanguages": [{"languageCode": "ta"}], "detectedBreak": {"type": "LINE_BREAK"}}, "boundingBox": {"vertices": [{"x": 256}, {"x": 272}, {"x": 272, "y": 35}, {"x": 256, "y": 35}]}, "text": "\u0bcd"}]}]}], "blockType": "TEXT"}]}], "text": "\u0bae\u0bc1\u0b9f\u0bbf \u0ba4\u0bbf\u0bb0\u0bc1\u0ba4\u0bcd\u0ba4\u0bc1\u0bae\u0bcd\n"}}