{"textAnnotations": [{"locale": "und", "description": "\u56ed\u56de\n", "boundingPoly": {"vertices": [{"x": 80, "y": 126}, {"x": 99, "y": 126}, {"x": 99, "y": 229}, {"x": 80, "y": 229}]}}, {"description": "\u56ed", "boundingPoly": {"vertices": [{"x": 100, "y": 126}, {"x": 99, "y": 203}, {"x": 81, "y": 203}, {"x": 82, "y": 126}]}}, {"description": "\u56de", "boundingPoly": {"vertices": [{"x": 99, "y": 205}, {"x": 99, "y": 229}, {"x": 81, "y": 229}, {"x": 81, "y": 205}]}}], "fullTextAnnotation": {"pages": [{"width": 375, "height": 500, "blocks": [{"boundingBox": {"vertices": [{"x": 100, "y": 126}, {"x": 98, "y": 229}, {"x": 80, "y": 229}, {"x": 82, "y": 126}]}, "paragraphs": [{"boundingBox": {"vertices": [{"x": 100, "y": 126}, {"x": 98, "y": 229}, {"x": 80, "y": 229}, {"x": 82, "y": 126}]}, "words": [{"boundingBox": {"vertices": [{"x": 100, "y": 126}, {"x": 99, "y": 203}, {"x": 81, "y": 203}, {"x": 82, "y": 126}]}, "symbols": [{"boundingBox": {"vertices": [{"x": 100, "y": 126}, {"x": 99, "y": 203}, {"x": 81, "y": 203}, {"x": 82, "y": 126}]}, "text": "\u56ed"}]}, {"boundingBox": {"vertices": [{"x": 99, "y": 205}, {"x": 99, "y": 229}, {"x": 81, "y": 229}, {"x": 81, "y": 205}]}, "symbols": [{"property": {"detectedBreak": {"type": "LINE_BREAK"}}, "boundingBox": {"vertices": [{"x": 99, "y": 205}, {"x": 99, "y": 229}, {"x": 81, "y": 229}, {"x": 81, "y": 205}]}, "text": "\u56de"}]}]}], "blockType": "TEXT"}]}], "text": "\u56ed\u56de\n"}}