{"textAnnotations": [{"locale": "en", "description": "PIGEON FORGE\nMOTOR LODGE\nHACARCY\nKING OUEEN EDS\nAMERICAN\nFAMLY ONNED\nWATER MOS\n15\n-1come\nFREE\nPANCAKE BREAKFASTI\nHBO\nMICRO FRI\nCOFFEE ELEVAT\n\u3057\n69\n", "boundingPoly": {"vertices": [{"x": 1, "y": 109}, {"x": 356, "y": 109}, {"x": 356, "y": 279}, {"x": 1, "y": 279}]}}, {"description": "PIGEON", "boundingPoly": {"vertices": [{"x": 204, "y": 109}, {"x": 258, "y": 113}, {"x": 256, "y": 136}, {"x": 202, "y": 132}]}}, {"description": "FORGE", "boundingPoly": {"vertices": [{"x": 260, "y": 113}, {"x": 304, "y": 116}, {"x": 302, "y": 138}, {"x": 258, "y": 135}]}}, {"description": "MOTOR", "boundingPoly": {"vertices": [{"x": 200, "y": 135}, {"x": 257, "y": 137}, {"x": 256, "y": 159}, {"x": 199, "y": 157}]}}, {"description": "LODGE", "boundingPoly": {"vertices": [{"x": 261, "y": 138}, {"x": 303, "y": 140}, {"x": 302, "y": 162}, {"x": 260, "y": 160}]}}, {"description": "HACARCY", "boundingPoly": {"vertices": [{"x": 212, "y": 170}, {"x": 240, "y": 171}, {"x": 240, "y": 176}, {"x": 212, "y": 175}]}}, {"description": "KING", "boundingPoly": {"vertices": [{"x": 196, "y": 178}, {"x": 207, "y": 178}, {"x": 207, "y": 185}, {"x": 196, "y": 185}]}}, {"description": "OUEEN", "boundingPoly": {"vertices": [{"x": 211, "y": 179}, {"x": 224, "y": 180}, {"x": 224, "y": 185}, {"x": 211, "y": 184}]}}, {"description": "EDS", "boundingPoly": {"vertices": [{"x": 228, "y": 179}, {"x": 239, "y": 179}, {"x": 239, "y": 185}, {"x": 228, "y": 185}]}}, {"description": "AMERICAN", "boundingPoly": {"vertices": [{"x": 210, "y": 184}, {"x": 233, "y": 186}, {"x": 232, "y": 193}, {"x": 209, "y": 191}]}}, {"description": "FAMLY", "boundingPoly": {"vertices": [{"x": 201, "y": 191}, {"x": 217, "y": 191}, {"x": 217, "y": 197}, {"x": 201, "y": 197}]}}, {"description": "ONNED", "boundingPoly": {"vertices": [{"x": 223, "y": 191}, {"x": 239, "y": 191}, {"x": 239, "y": 197}, {"x": 223, "y": 197}]}}, {"description": "WATER", "boundingPoly": {"vertices": [{"x": 202, "y": 199}, {"x": 218, "y": 199}, {"x": 218, "y": 204}, {"x": 202, "y": 204}]}}, {"description": "MOS", "boundingPoly": {"vertices": [{"x": 224, "y": 198}, {"x": 234, "y": 198}, {"x": 234, "y": 205}, {"x": 224, "y": 205}]}}, {"description": "15", "boundingPoly": {"vertices": [{"x": 333, "y": 214}, {"x": 355, "y": 223}, {"x": 350, "y": 237}, {"x": 328, "y": 228}]}}, {"description": "-1come", "boundingPoly": {"vertices": [{"x": 1, "y": 216}, {"x": 28, "y": 217}, {"x": 28, "y": 224}, {"x": 1, "y": 223}]}}, {"description": "FREE", "boundingPoly": {"vertices": [{"x": 301, "y": 226}, {"x": 314, "y": 226}, {"x": 314, "y": 232}, {"x": 301, "y": 232}]}}, {"description": "PANCAKE", "boundingPoly": {"vertices": [{"x": 283, "y": 234}, {"x": 314, "y": 233}, {"x": 314, "y": 242}, {"x": 283, "y": 243}]}}, {"description": "BREAKFASTI", "boundingPoly": {"vertices": [{"x": 317, "y": 233}, {"x": 356, "y": 232}, {"x": 356, "y": 242}, {"x": 317, "y": 243}]}}, {"description": "HBO", "boundingPoly": {"vertices": [{"x": 292, "y": 242}, {"x": 302, "y": 242}, {"x": 302, "y": 251}, {"x": 292, "y": 251}]}}, {"description": "MICRO", "boundingPoly": {"vertices": [{"x": 317, "y": 241}, {"x": 335, "y": 241}, {"x": 335, "y": 250}, {"x": 317, "y": 250}]}}, {"description": "FRI", "boundingPoly": {"vertices": [{"x": 337, "y": 240}, {"x": 345, "y": 240}, {"x": 345, "y": 250}, {"x": 337, "y": 250}]}}, {"description": "COFFEE", "boundingPoly": {"vertices": [{"x": 300, "y": 251}, {"x": 319, "y": 251}, {"x": 319, "y": 258}, {"x": 300, "y": 258}]}}, {"description": "ELEVAT", "boundingPoly": {"vertices": [{"x": 326, "y": 249}, {"x": 348, "y": 248}, {"x": 348, "y": 258}, {"x": 326, "y": 259}]}}, {"description": "\u3057", "boundingPoly": {"vertices": [{"x": 353, "y": 217}, {"x": 354, "y": 245}, {"x": 345, "y": 245}, {"x": 344, "y": 217}]}}, {"description": "69", "boundingPoly": {"vertices": [{"x": 121, "y": 267}, {"x": 121, "y": 279}, {"x": 111, "y": 279}, {"x": 110, "y": 267}]}}], "fullTextAnnotation": {"pages": [{"property": {"detectedLanguages": [{"languageCode": "en", "confidence": 0.74}, {"languageCode": "ca", "confidence": 0.1}, {"languageCode": "da", "confidence": 0.07}]}, "width": 500, "height": 333, "blocks": [{"property": {"detectedLanguages": [{"languageCode": "en", "confidence": 1.0}]}, "boundingBox": {"vertices": [{"x": 201, "y": 109}, {"x": 305, "y": 115}, {"x": 302, "y": 163}, {"x": 198, "y": 157}]}, "paragraphs": [{"property": {"detectedLanguages": [{"languageCode": "en", "confidence": 1.0}]}, "boundingBox": {"vertices": [{"x": 201, "y": 109}, {"x": 305, "y": 115}, {"x": 302, "y": 163}, {"x": 198, "y": 157}]}, "words": [{"property": {"detectedLanguages": [{"languageCode": "en"}]}, "boundingBox": {"vertices": [{"x": 204, "y": 109}, {"x": 258, "y": 113}, {"x": 256, "y": 136}, {"x": 202, "y": 132}]}, "symbols": [{"property": {"detectedLanguages": [{"languageCode": "en"}]}, "boundingBox": {"vertices": [{"x": 204, "y": 110}, {"x": 219, "y": 111}, {"x": 217, "y": 133}, {"x": 202, "y": 132}]}, "text": "P"}, {"property": {"detectedLanguages": [{"languageCode": "en"}]}, "boundingBox": {"vertices": [{"x": 220, "y": 111}, {"x": 223, "y": 111}, {"x": 221, "y": 133}, {"x": 218, "y": 133}]}, "text": "I"}, {"property": {"detectedLanguages": [{"languageCode": "en"}]}, "boundingBox": {"vertices": [{"x": 224, "y": 111}, {"x": 235, "y": 112}, {"x": 233, "y": 134}, {"x": 222, "y": 133}]}, "text": "G"}, {"property": {"detectedLanguages": [{"languageCode": "en"}]}, "boundingBox": {"vertices": [{"x": 236, "y": 112}, {"x": 242, "y": 112}, {"x": 240, "y": 134}, {"x": 234, "y": 134}]}, "text": "E"}, {"property": {"detectedLanguages": [{"languageCode": "en"}]}, "boundingBox": {"vertices": [{"x": 243, "y": 112}, {"x": 254, "y": 113}, {"x": 252, "y": 135}, {"x": 241, "y": 134}]}, "text": "O"}, {"property": {"detectedLanguages": [{"languageCode": "en"}], "detectedBreak": {"type": "SPACE"}}, "boundingBox": {"vertices": [{"x": 255, "y": 113}, {"x": 258, "y": 113}, {"x": 256, "y": 135}, {"x": 253, "y": 135}]}, "text": "N"}]}, {"property": {"detectedLanguages": [{"languageCode": "en"}]}, "boundingBox": {"vertices": [{"x": 260, "y": 113}, {"x": 304, "y": 116}, {"x": 302, "y": 138}, {"x": 258, "y": 135}]}, "symbols": [{"property": {"detectedLanguages": [{"languageCode": "en"}]}, "boundingBox": {"vertices": [{"x": 260, "y": 113}, {"x": 273, "y": 114}, {"x": 271, "y": 136}, {"x": 258, "y": 135}]}, "text": "F"}, {"property": {"detectedLanguages": [{"languageCode": "en"}]}, "boundingBox": {"vertices": [{"x": 274, "y": 114}, {"x": 281, "y": 114}, {"x": 279, "y": 136}, {"x": 272, "y": 136}]}, "text": "O"}, {"property": {"detectedLanguages": [{"languageCode": "en"}]}, "boundingBox": {"vertices": [{"x": 282, "y": 115}, {"x": 288, "y": 115}, {"x": 286, "y": 137}, {"x": 280, "y": 137}]}, "text": "R"}, {"property": {"detectedLanguages": [{"languageCode": "en"}]}, "boundingBox": {"vertices": [{"x": 289, "y": 115}, {"x": 300, "y": 116}, {"x": 298, "y": 138}, {"x": 287, "y": 137}]}, "text": "G"}, {"property": {"detectedLanguages": [{"languageCode": "en"}], "detectedBreak": {"type": "EOL_SURE_SPACE"}}, "boundingBox": {"vertices": [{"x": 301, "y": 116}, {"x": 304, "y": 116}, {"x": 302, "y": 138}, {"x": 299, "y": 138}]}, "text": "E"}]}, {"property": {"detectedLanguages": [{"languageCode": "en"}]}, "boundingBox": {"vertices": [{"x": 200, "y": 135}, {"x": 257, "y": 137}, {"x": 256, "y": 159}, {"x": 199, "y": 157}]}, "symbols": [{"property": {"detectedLanguages": [{"languageCode": "en"}]}, "boundingBox": {"vertices": [{"x": 200, "y": 136}, {"x": 219, "y": 137}, {"x": 218, "y": 158}, {"x": 199, "y": 157}]}, "text": "M"}, {"property": {"detectedLanguages": [{"languageCode": "en"}]}, "boundingBox": {"vertices": [{"x": 220, "y": 137}, {"x": 233, "y": 138}, {"x": 232, "y": 159}, {"x": 219, "y": 158}]}, "text": "O"}, {"property": {"detectedLanguages": [{"languageCode": "en"}]}, "boundingBox": {"vertices": [{"x": 234, "y": 136}, {"x": 237, "y": 136}, {"x": 236, "y": 157}, {"x": 233, "y": 157}]}, "text": "T"}, {"property": {"detectedLanguages": [{"languageCode": "en"}]}, "boundingBox": {"vertices": [{"x": 238, "y": 138}, {"x": 248, "y": 138}, {"x": 247, "y": 159}, {"x": 237, "y": 159}]}, "text": "O"}, {"property": {"detectedLanguages": [{"languageCode": "en"}], "detectedBreak": {"type": "SPACE"}}, "boundingBox": {"vertices": [{"x": 249, "y": 138}, {"x": 257, "y": 138}, {"x": 256, "y": 159}, {"x": 248, "y": 159}]}, "text": "R"}]}, {"property": {"detectedLanguages": [{"languageCode": "en"}]}, "boundingBox": {"vertices": [{"x": 261, "y": 138}, {"x": 303, "y": 140}, {"x": 302, "y": 162}, {"x": 260, "y": 160}]}, "symbols": [{"property": {"detectedLanguages": [{"languageCode": "en"}]}, "boundingBox": {"vertices": [{"x": 261, "y": 139}, {"x": 274, "y": 140}, {"x": 273, "y": 161}, {"x": 260, "y": 160}]}, "text": "L"}, {"property": {"detectedLanguages": [{"languageCode": "en"}]}, "boundingBox": {"vertices": [{"x": 275, "y": 139}, {"x": 281, "y": 139}, {"x": 280, "y": 160}, {"x": 274, "y": 160}]}, "text": "O"}, {"property": {"detectedLanguages": [{"languageCode": "en"}]}, "boundingBox": {"vertices": [{"x": 282, "y": 140}, {"x": 288, "y": 140}, {"x": 287, "y": 161}, {"x": 281, "y": 161}]}, "text": "D"}, {"property": {"detectedLanguages": [{"languageCode": "en"}]}, "boundingBox": {"vertices": [{"x": 289, "y": 140}, {"x": 299, "y": 140}, {"x": 298, "y": 161}, {"x": 288, "y": 161}]}, "text": "G"}, {"property": {"detectedLanguages": [{"languageCode": "en"}], "detectedBreak": {"type": "LINE_BREAK"}}, "boundingBox": {"vertices": [{"x": 300, "y": 140}, {"x": 303, "y": 140}, {"x": 302, "y": 161}, {"x": 299, "y": 161}]}, "text": "E"}]}]}], "blockType": "TEXT"}, {"property": {"detectedLanguages": [{"languageCode": "en", "confidence": 1.0}]}, "boundingBox": {"vertices": [{"x": 212, "y": 170}, {"x": 240, "y": 171}, {"x": 240, "y": 176}, {"x": 212, "y": 175}]}, "paragraphs": [{"property": {"detectedLanguages": [{"languageCode": "en", "confidence": 1.0}]}, "boundingBox": {"vertices": [{"x": 212, "y": 170}, {"x": 240, "y": 171}, {"x": 240, "y": 176}, {"x": 212, "y": 175}]}, "words": [{"property": {"detectedLanguages": [{"languageCode": "en"}]}, "boundingBox": {"vertices": [{"x": 212, "y": 170}, {"x": 240, "y": 171}, {"x": 240, "y": 176}, {"x": 212, "y": 175}]}, "symbols": [{"property": {"detectedLanguages": [{"languageCode": "en"}]}, "boundingBox": {"vertices": [{"x": 212, "y": 170}, {"x": 219, "y": 170}, {"x": 219, "y": 175}, {"x": 212, "y": 175}]}, "text": "H"}, {"property": {"detectedLanguages": [{"languageCode": "en"}]}, "boundingBox": {"vertices": [{"x": 220, "y": 170}, {"x": 223, "y": 170}, {"x": 223, "y": 175}, {"x": 220, "y": 175}]}, "text": "A"}, {"property": {"detectedLanguages": [{"languageCode": "en"}]}, "boundingBox": {"vertices": [{"x": 224, "y": 171}, {"x": 226, "y": 171}, {"x": 226, "y": 176}, {"x": 224, "y": 176}]}, "text": "C"}, {"property": {"detectedLanguages": [{"languageCode": "en"}]}, "boundingBox": {"vertices": [{"x": 227, "y": 171}, {"x": 230, "y": 171}, {"x": 230, "y": 176}, {"x": 227, "y": 176}]}, "text": "A"}, {"property": {"detectedLanguages": [{"languageCode": "en"}]}, "boundingBox": {"vertices": [{"x": 231, "y": 171}, {"x": 234, "y": 171}, {"x": 234, "y": 176}, {"x": 231, "y": 176}]}, "text": "R"}, {"property": {"detectedLanguages": [{"languageCode": "en"}]}, "boundingBox": {"vertices": [{"x": 235, "y": 171}, {"x": 237, "y": 171}, {"x": 237, "y": 176}, {"x": 235, "y": 176}]}, "text": "C"}, {"property": {"detectedLanguages": [{"languageCode": "en"}], "detectedBreak": {"type": "LINE_BREAK"}}, "boundingBox": {"vertices": [{"x": 238, "y": 171}, {"x": 240, "y": 171}, {"x": 240, "y": 176}, {"x": 238, "y": 176}]}, "text": "Y"}]}]}], "blockType": "TEXT"}, {"property": {"detectedLanguages": [{"languageCode": "en", "confidence": 1.0}]}, "boundingBox": {"vertices": [{"x": 196, "y": 178}, {"x": 239, "y": 179}, {"x": 238, "y": 205}, {"x": 195, "y": 204}]}, "paragraphs": [{"property": {"detectedLanguages": [{"languageCode": "en", "confidence": 1.0}]}, "boundingBox": {"vertices": [{"x": 196, "y": 178}, {"x": 239, "y": 179}, {"x": 238, "y": 205}, {"x": 195, "y": 204}]}, "words": [{"property": {"detectedLanguages": [{"languageCode": "en"}]}, "boundingBox": {"vertices": [{"x": 196, "y": 178}, {"x": 207, "y": 178}, {"x": 207, "y": 185}, {"x": 196, "y": 185}]}, "symbols": [{"property": {"detectedLanguages": [{"languageCode": "en"}]}, "boundingBox": {"vertices": [{"x": 196, "y": 178}, {"x": 201, "y": 178}, {"x": 201, "y": 184}, {"x": 196, "y": 184}]}, "text": "K"}, {"property": {"detectedLanguages": [{"languageCode": "en"}]}, "boundingBox": {"vertices": [{"x": 202, "y": 178}, {"x": 204, "y": 178}, {"x": 204, "y": 184}, {"x": 202, "y": 184}]}, "text": "I"}, {"property": {"detectedLanguages": [{"languageCode": "en"}]}, "boundingBox": {"vertices": [{"x": 205, "y": 179}, {"x": 205, "y": 179}, {"x": 205, "y": 185}, {"x": 205, "y": 185}]}, "text": "N"}, {"property": {"detectedLanguages": [{"languageCode": "en"}], "detectedBreak": {"type": "SPACE"}}, "boundingBox": {"vertices": [{"x": 206, "y": 179}, {"x": 207, "y": 179}, {"x": 207, "y": 185}, {"x": 206, "y": 185}]}, "text": "G"}]}, {"property": {"detectedLanguages": [{"languageCode": "en"}]}, "boundingBox": {"vertices": [{"x": 211, "y": 179}, {"x": 224, "y": 180}, {"x": 224, "y": 185}, {"x": 211, "y": 184}]}, "symbols": [{"property": {"detectedLanguages": [{"languageCode": "en"}]}, "boundingBox": {"vertices": [{"x": 211, "y": 180}, {"x": 214, "y": 180}, {"x": 214, "y": 184}, {"x": 211, "y": 184}]}, "text": "O"}, {"property": {"detectedLanguages": [{"languageCode": "en"}]}, "boundingBox": {"vertices": [{"x": 215, "y": 180}, {"x": 217, "y": 180}, {"x": 217, "y": 184}, {"x": 215, "y": 184}]}, "text": "U"}, {"property": {"detectedLanguages": [{"languageCode": "en"}]}, "boundingBox": {"vertices": [{"x": 218, "y": 180}, {"x": 219, "y": 180}, {"x": 219, "y": 184}, {"x": 218, "y": 184}]}, "text": "E"}, {"property": {"detectedLanguages": [{"languageCode": "en"}]}, "boundingBox": {"vertices": [{"x": 220, "y": 180}, {"x": 222, "y": 180}, {"x": 222, "y": 184}, {"x": 220, "y": 184}]}, "text": "E"}, {"property": {"detectedLanguages": [{"languageCode": "en"}], "detectedBreak": {"type": "SPACE"}}, "boundingBox": {"vertices": [{"x": 223, "y": 180}, {"x": 224, "y": 180}, {"x": 224, "y": 184}, {"x": 223, "y": 184}]}, "text": "N"}]}, {"property": {"detectedLanguages": [{"languageCode": "en"}]}, "boundingBox": {"vertices": [{"x": 228, "y": 179}, {"x": 239, "y": 179}, {"x": 239, "y": 185}, {"x": 228, "y": 185}]}, "symbols": [{"property": {"detectedLanguages": [{"languageCode": "en"}]}, "boundingBox": {"vertices": [{"x": 228, "y": 179}, {"x": 232, "y": 179}, {"x": 232, "y": 184}, {"x": 228, "y": 184}]}, "text": "E"}, {"property": {"detectedLanguages": [{"languageCode": "en"}]}, "boundingBox": {"vertices": [{"x": 233, "y": 180}, {"x": 234, "y": 180}, {"x": 234, "y": 185}, {"x": 233, "y": 185}]}, "text": "D"}, {"property": {"detectedLanguages": [{"languageCode": "en"}], "detectedBreak": {"type": "EOL_SURE_SPACE"}}, "boundingBox": {"vertices": [{"x": 235, "y": 180}, {"x": 239, "y": 180}, {"x": 239, "y": 185}, {"x": 235, "y": 185}]}, "text": "S"}]}, {"property": {"detectedLanguages": [{"languageCode": "en"}]}, "boundingBox": {"vertices": [{"x": 210, "y": 184}, {"x": 233, "y": 186}, {"x": 232, "y": 193}, {"x": 209, "y": 191}]}, "symbols": [{"property": {"detectedLanguages": [{"languageCode": "en"}]}, "boundingBox": {"vertices": [{"x": 210, "y": 184}, {"x": 214, "y": 184}, {"x": 214, "y": 190}, {"x": 210, "y": 190}]}, "text": "A"}, {"property": {"detectedLanguages": [{"languageCode": "en"}]}, "boundingBox": {"vertices": [{"x": 215, "y": 185}, {"x": 218, "y": 185}, {"x": 218, "y": 191}, {"x": 215, "y": 191}]}, "text": "M"}, {"property": {"detectedLanguages": [{"languageCode": "en"}]}, "boundingBox": {"vertices": [{"x": 219, "y": 185}, {"x": 220, "y": 185}, {"x": 220, "y": 191}, {"x": 219, "y": 191}]}, "text": "E"}, {"property": {"detectedLanguages": [{"languageCode": "en"}]}, "boundingBox": {"vertices": [{"x": 221, "y": 185}, {"x": 224, "y": 185}, {"x": 224, "y": 191}, {"x": 221, "y": 191}]}, "text": "R"}, {"property": {"detectedLanguages": [{"languageCode": "en"}]}, "boundingBox": {"vertices": [{"x": 225, "y": 185}, {"x": 226, "y": 185}, {"x": 226, "y": 191}, {"x": 225, "y": 191}]}, "text": "I"}, {"property": {"detectedLanguages": [{"languageCode": "en"}]}, "boundingBox": {"vertices": [{"x": 227, "y": 185}, {"x": 228, "y": 185}, {"x": 228, "y": 191}, {"x": 227, "y": 191}]}, "text": "C"}, {"property": {"detectedLanguages": [{"languageCode": "en"}]}, "boundingBox": {"vertices": [{"x": 229, "y": 186}, {"x": 231, "y": 186}, {"x": 231, "y": 192}, {"x": 229, "y": 192}]}, "text": "A"}, {"property": {"detectedLanguages": [{"languageCode": "en"}], "detectedBreak": {"type": "EOL_SURE_SPACE"}}, "boundingBox": {"vertices": [{"x": 232, "y": 186}, {"x": 233, "y": 186}, {"x": 233, "y": 192}, {"x": 232, "y": 192}]}, "text": "N"}]}, {"property": {"detectedLanguages": [{"languageCode": "en"}]}, "boundingBox": {"vertices": [{"x": 201, "y": 191}, {"x": 217, "y": 191}, {"x": 217, "y": 197}, {"x": 201, "y": 197}]}, "symbols": [{"property": {"detectedLanguages": [{"languageCode": "en"}]}, "boundingBox": {"vertices": [{"x": 201, "y": 191}, {"x": 204, "y": 191}, {"x": 204, "y": 197}, {"x": 201, "y": 197}]}, "text": "F"}, {"property": {"detectedLanguages": [{"languageCode": "en"}]}, "boundingBox": {"vertices": [{"x": 205, "y": 191}, {"x": 207, "y": 191}, {"x": 207, "y": 197}, {"x": 205, "y": 197}]}, "text": "A"}, {"property": {"detectedLanguages": [{"languageCode": "en"}]}, "boundingBox": {"vertices": [{"x": 209, "y": 191}, {"x": 211, "y": 191}, {"x": 211, "y": 197}, {"x": 209, "y": 197}]}, "text": "M"}, {"property": {"detectedLanguages": [{"languageCode": "en"}]}, "boundingBox": {"vertices": [{"x": 212, "y": 191}, {"x": 216, "y": 191}, {"x": 216, "y": 197}, {"x": 212, "y": 197}]}, "text": "L"}, {"property": {"detectedLanguages": [{"languageCode": "en"}], "detectedBreak": {"type": "SPACE"}}, "boundingBox": {"vertices": [{"x": 216, "y": 191}, {"x": 217, "y": 191}, {"x": 217, "y": 197}, {"x": 216, "y": 197}]}, "text": "Y"}]}, {"property": {"detectedLanguages": [{"languageCode": "en"}]}, "boundingBox": {"vertices": [{"x": 223, "y": 191}, {"x": 239, "y": 191}, {"x": 239, "y": 197}, {"x": 223, "y": 197}]}, "symbols": [{"property": {"detectedLanguages": [{"languageCode": "en"}]}, "boundingBox": {"vertices": [{"x": 223, "y": 191}, {"x": 229, "y": 191}, {"x": 229, "y": 197}, {"x": 223, "y": 197}]}, "text": "O"}, {"property": {"detectedLanguages": [{"languageCode": "en"}]}, "boundingBox": {"vertices": [{"x": 229, "y": 191}, {"x": 230, "y": 191}, {"x": 230, "y": 197}, {"x": 229, "y": 197}]}, "text": "N"}, {"property": {"detectedLanguages": [{"languageCode": "en"}]}, "boundingBox": {"vertices": [{"x": 231, "y": 191}, {"x": 234, "y": 191}, {"x": 234, "y": 197}, {"x": 231, "y": 197}]}, "text": "N"}, {"property": {"detectedLanguages": [{"languageCode": "en"}]}, "boundingBox": {"vertices": [{"x": 236, "y": 191}, {"x": 236, "y": 191}, {"x": 236, "y": 197}, {"x": 236, "y": 197}]}, "text": "E"}, {"property": {"detectedLanguages": [{"languageCode": "en"}], "detectedBreak": {"type": "EOL_SURE_SPACE"}}, "boundingBox": {"vertices": [{"x": 237, "y": 191}, {"x": 239, "y": 191}, {"x": 239, "y": 197}, {"x": 237, "y": 197}]}, "text": "D"}]}, {"property": {"detectedLanguages": [{"languageCode": "en"}]}, "boundingBox": {"vertices": [{"x": 202, "y": 199}, {"x": 218, "y": 199}, {"x": 218, "y": 204}, {"x": 202, "y": 204}]}, "symbols": [{"property": {"detectedLanguages": [{"languageCode": "en"}]}, "boundingBox": {"vertices": [{"x": 202, "y": 199}, {"x": 208, "y": 199}, {"x": 208, "y": 204}, {"x": 202, "y": 204}]}, "text": "W"}, {"property": {"detectedLanguages": [{"languageCode": "en"}]}, "boundingBox": {"vertices": [{"x": 209, "y": 199}, {"x": 209, "y": 199}, {"x": 209, "y": 204}, {"x": 209, "y": 204}]}, "text": "A"}, {"property": {"detectedLanguages": [{"languageCode": "en"}]}, "boundingBox": {"vertices": [{"x": 210, "y": 199}, {"x": 213, "y": 199}, {"x": 213, "y": 204}, {"x": 210, "y": 204}]}, "text": "T"}, {"property": {"detectedLanguages": [{"languageCode": "en"}]}, "boundingBox": {"vertices": [{"x": 214, "y": 199}, {"x": 216, "y": 199}, {"x": 216, "y": 204}, {"x": 214, "y": 204}]}, "text": "E"}, {"property": {"detectedLanguages": [{"languageCode": "en"}], "detectedBreak": {"type": "SPACE"}}, "boundingBox": {"vertices": [{"x": 217, "y": 199}, {"x": 218, "y": 199}, {"x": 218, "y": 204}, {"x": 217, "y": 204}]}, "text": "R"}]}, {"property": {"detectedLanguages": [{"languageCode": "en"}]}, "boundingBox": {"vertices": [{"x": 224, "y": 198}, {"x": 234, "y": 198}, {"x": 234, "y": 205}, {"x": 224, "y": 205}]}, "symbols": [{"property": {"detectedLanguages": [{"languageCode": "en"}]}, "boundingBox": {"vertices": [{"x": 224, "y": 198}, {"x": 227, "y": 198}, {"x": 227, "y": 204}, {"x": 224, "y": 204}]}, "text": "M"}, {"property": {"detectedLanguages": [{"languageCode": "en"}]}, "boundingBox": {"vertices": [{"x": 229, "y": 198}, {"x": 231, "y": 198}, {"x": 231, "y": 204}, {"x": 229, "y": 204}]}, "text": "O"}, {"property": {"detectedLanguages": [{"languageCode": "en"}], "detectedBreak": {"type": "LINE_BREAK"}}, "boundingBox": {"vertices": [{"x": 233, "y": 199}, {"x": 234, "y": 199}, {"x": 234, "y": 205}, {"x": 233, "y": 205}]}, "text": "S"}]}]}], "blockType": "TEXT"}, {"boundingBox": {"vertices": [{"x": 333, "y": 214}, {"x": 355, "y": 223}, {"x": 350, "y": 237}, {"x": 328, "y": 228}]}, "paragraphs": [{"boundingBox": {"vertices": [{"x": 333, "y": 214}, {"x": 355, "y": 223}, {"x": 350, "y": 237}, {"x": 328, "y": 228}]}, "words": [{"boundingBox": {"vertices": [{"x": 333, "y": 214}, {"x": 355, "y": 223}, {"x": 350, "y": 237}, {"x": 328, "y": 228}]}, "symbols": [{"boundingBox": {"vertices": [{"x": 333, "y": 214}, {"x": 345, "y": 219}, {"x": 340, "y": 233}, {"x": 328, "y": 228}]}, "text": "1"}, {"property": {"detectedBreak": {"type": "LINE_BREAK"}}, "boundingBox": {"vertices": [{"x": 346, "y": 219}, {"x": 355, "y": 223}, {"x": 350, "y": 237}, {"x": 341, "y": 233}]}, "text": "5"}]}]}], "blockType": "TEXT"}, {"property": {"detectedLanguages": [{"languageCode": "en", "confidence": 1.0}]}, "boundingBox": {"vertices": [{"x": 1, "y": 216}, {"x": 28, "y": 217}, {"x": 28, "y": 224}, {"x": 1, "y": 223}]}, "paragraphs": [{"property": {"detectedLanguages": [{"languageCode": "en", "confidence": 1.0}]}, "boundingBox": {"vertices": [{"x": 1, "y": 216}, {"x": 28, "y": 217}, {"x": 28, "y": 224}, {"x": 1, "y": 223}]}, "words": [{"property": {"detectedLanguages": [{"languageCode": "en"}]}, "boundingBox": {"vertices": [{"x": 1, "y": 216}, {"x": 28, "y": 217}, {"x": 28, "y": 224}, {"x": 1, "y": 223}]}, "symbols": [{"property": {"detectedLanguages": [{"languageCode": "en"}]}, "boundingBox": {"vertices": [{"x": 1, "y": 216}, {"x": 4, "y": 216}, {"x": 4, "y": 223}, {"x": 1, "y": 223}]}, "text": "-"}, {"property": {"detectedLanguages": [{"languageCode": "en"}]}, "boundingBox": {"vertices": [{"x": 5, "y": 216}, {"x": 13, "y": 216}, {"x": 13, "y": 223}, {"x": 5, "y": 223}]}, "text": "1"}, {"property": {"detectedLanguages": [{"languageCode": "en"}]}, "boundingBox": {"vertices": [{"x": 14, "y": 217}, {"x": 17, "y": 217}, {"x": 17, "y": 224}, {"x": 14, "y": 224}]}, "text": "c"}, {"property": {"detectedLanguages": [{"languageCode": "en"}]}, "boundingBox": {"vertices": [{"x": 18, "y": 217}, {"x": 23, "y": 217}, {"x": 23, "y": 224}, {"x": 18, "y": 224}]}, "text": "o"}, {"property": {"detectedLanguages": [{"languageCode": "en"}]}, "boundingBox": {"vertices": [{"x": 24, "y": 217}, {"x": 27, "y": 217}, {"x": 27, "y": 224}, {"x": 24, "y": 224}]}, "text": "m"}, {"property": {"detectedLanguages": [{"languageCode": "en"}], "detectedBreak": {"type": "LINE_BREAK"}}, "boundingBox": {"vertices": [{"x": 28, "y": 217}, {"x": 28, "y": 217}, {"x": 28, "y": 224}, {"x": 28, "y": 224}]}, "text": "e"}]}]}], "blockType": "TEXT"}, {"boundingBox": {"vertices": [{"x": 301, "y": 226}, {"x": 314, "y": 226}, {"x": 314, "y": 232}, {"x": 301, "y": 232}]}, "paragraphs": [{"boundingBox": {"vertices": [{"x": 301, "y": 226}, {"x": 314, "y": 226}, {"x": 314, "y": 232}, {"x": 301, "y": 232}]}, "words": [{"boundingBox": {"vertices": [{"x": 301, "y": 226}, {"x": 314, "y": 226}, {"x": 314, "y": 232}, {"x": 301, "y": 232}]}, "symbols": [{"boundingBox": {"vertices": [{"x": 301, "y": 226}, {"x": 307, "y": 226}, {"x": 307, "y": 232}, {"x": 301, "y": 232}]}, "text": "F"}, {"boundingBox": {"vertices": [{"x": 308, "y": 226}, {"x": 309, "y": 226}, {"x": 309, "y": 232}, {"x": 308, "y": 232}]}, "text": "R"}, {"boundingBox": {"vertices": [{"x": 310, "y": 226}, {"x": 312, "y": 226}, {"x": 312, "y": 232}, {"x": 310, "y": 232}]}, "text": "E"}, {"property": {"detectedBreak": {"type": "LINE_BREAK"}}, "boundingBox": {"vertices": [{"x": 313, "y": 226}, {"x": 314, "y": 226}, {"x": 314, "y": 232}, {"x": 313, "y": 232}]}, "text": "E"}]}]}], "blockType": "TEXT"}, {"property": {"detectedLanguages": [{"languageCode": "en", "confidence": 1.0}]}, "boundingBox": {"vertices": [{"x": 283, "y": 234}, {"x": 356, "y": 233}, {"x": 356, "y": 243}, {"x": 283, "y": 244}]}, "paragraphs": [{"property": {"detectedLanguages": [{"languageCode": "en", "confidence": 1.0}]}, "boundingBox": {"vertices": [{"x": 283, "y": 234}, {"x": 356, "y": 233}, {"x": 356, "y": 243}, {"x": 283, "y": 244}]}, "words": [{"property": {"detectedLanguages": [{"languageCode": "en"}]}, "boundingBox": {"vertices": [{"x": 283, "y": 234}, {"x": 314, "y": 233}, {"x": 314, "y": 242}, {"x": 283, "y": 243}]}, "symbols": [{"property": {"detectedLanguages": [{"languageCode": "en"}]}, "boundingBox": {"vertices": [{"x": 283, "y": 234}, {"x": 291, "y": 234}, {"x": 291, "y": 243}, {"x": 283, "y": 243}]}, "text": "P"}, {"property": {"detectedLanguages": [{"languageCode": "en"}]}, "boundingBox": {"vertices": [{"x": 292, "y": 234}, {"x": 294, "y": 234}, {"x": 294, "y": 243}, {"x": 292, "y": 243}]}, "text": "A"}, {"property": {"detectedLanguages": [{"languageCode": "en"}]}, "boundingBox": {"vertices": [{"x": 295, "y": 234}, {"x": 299, "y": 234}, {"x": 299, "y": 243}, {"x": 295, "y": 243}]}, "text": "N"}, {"property": {"detectedLanguages": [{"languageCode": "en"}]}, "boundingBox": {"vertices": [{"x": 300, "y": 234}, {"x": 304, "y": 234}, {"x": 304, "y": 243}, {"x": 300, "y": 243}]}, "text": "C"}, {"property": {"detectedLanguages": [{"languageCode": "en"}]}, "boundingBox": {"vertices": [{"x": 305, "y": 234}, {"x": 307, "y": 234}, {"x": 307, "y": 243}, {"x": 305, "y": 243}]}, "text": "A"}, {"property": {"detectedLanguages": [{"languageCode": "en"}]}, "boundingBox": {"vertices": [{"x": 308, "y": 234}, {"x": 311, "y": 234}, {"x": 311, "y": 243}, {"x": 308, "y": 243}]}, "text": "K"}, {"property": {"detectedLanguages": [{"languageCode": "en"}], "detectedBreak": {"type": "SPACE"}}, "boundingBox": {"vertices": [{"x": 312, "y": 233}, {"x": 314, "y": 233}, {"x": 314, "y": 242}, {"x": 312, "y": 242}]}, "text": "E"}]}, {"property": {"detectedLanguages": [{"languageCode": "en"}]}, "boundingBox": {"vertices": [{"x": 317, "y": 233}, {"x": 356, "y": 232}, {"x": 356, "y": 242}, {"x": 317, "y": 243}]}, "symbols": [{"property": {"detectedLanguages": [{"languageCode": "en"}]}, "boundingBox": {"vertices": [{"x": 317, "y": 233}, {"x": 322, "y": 233}, {"x": 322, "y": 242}, {"x": 317, "y": 242}]}, "text": "B"}, {"property": {"detectedLanguages": [{"languageCode": "en"}]}, "boundingBox": {"vertices": [{"x": 323, "y": 233}, {"x": 327, "y": 233}, {"x": 327, "y": 242}, {"x": 323, "y": 242}]}, "text": "R"}, {"property": {"detectedLanguages": [{"languageCode": "en"}]}, "boundingBox": {"vertices": [{"x": 328, "y": 233}, {"x": 331, "y": 233}, {"x": 331, "y": 242}, {"x": 328, "y": 242}]}, "text": "E"}, {"property": {"detectedLanguages": [{"languageCode": "en"}]}, "boundingBox": {"vertices": [{"x": 332, "y": 233}, {"x": 334, "y": 233}, {"x": 334, "y": 242}, {"x": 332, "y": 242}]}, "text": "A"}, {"property": {"detectedLanguages": [{"languageCode": "en"}]}, "boundingBox": {"vertices": [{"x": 335, "y": 233}, {"x": 337, "y": 233}, {"x": 337, "y": 242}, {"x": 335, "y": 242}]}, "text": "K"}, {"property": {"detectedLanguages": [{"languageCode": "en"}]}, "boundingBox": {"vertices": [{"x": 338, "y": 233}, {"x": 341, "y": 233}, {"x": 341, "y": 242}, {"x": 338, "y": 242}]}, "text": "F"}, {"property": {"detectedLanguages": [{"languageCode": "en"}]}, "boundingBox": {"vertices": [{"x": 342, "y": 233}, {"x": 344, "y": 233}, {"x": 344, "y": 242}, {"x": 342, "y": 242}]}, "text": "A"}, {"property": {"detectedLanguages": [{"languageCode": "en"}]}, "boundingBox": {"vertices": [{"x": 345, "y": 233}, {"x": 351, "y": 233}, {"x": 351, "y": 242}, {"x": 345, "y": 242}]}, "text": "S"}, {"property": {"detectedLanguages": [{"languageCode": "en"}]}, "boundingBox": {"vertices": [{"x": 352, "y": 233}, {"x": 352, "y": 233}, {"x": 352, "y": 242}, {"x": 352, "y": 242}]}, "text": "T"}, {"property": {"detectedLanguages": [{"languageCode": "en"}], "detectedBreak": {"type": "LINE_BREAK"}}, "boundingBox": {"vertices": [{"x": 353, "y": 233}, {"x": 356, "y": 233}, {"x": 356, "y": 242}, {"x": 353, "y": 242}]}, "text": "I"}]}]}], "blockType": "TEXT"}, {"boundingBox": {"vertices": [{"x": 292, "y": 242}, {"x": 302, "y": 242}, {"x": 302, "y": 251}, {"x": 292, "y": 251}]}, "paragraphs": [{"boundingBox": {"vertices": [{"x": 292, "y": 242}, {"x": 302, "y": 242}, {"x": 302, "y": 251}, {"x": 292, "y": 251}]}, "words": [{"boundingBox": {"vertices": [{"x": 292, "y": 242}, {"x": 302, "y": 242}, {"x": 302, "y": 251}, {"x": 292, "y": 251}]}, "symbols": [{"boundingBox": {"vertices": [{"x": 292, "y": 242}, {"x": 295, "y": 242}, {"x": 295, "y": 251}, {"x": 292, "y": 251}]}, "text": "H"}, {"boundingBox": {"vertices": [{"x": 296, "y": 242}, {"x": 300, "y": 242}, {"x": 300, "y": 251}, {"x": 296, "y": 251}]}, "text": "B"}, {"property": {"detectedBreak": {"type": "LINE_BREAK"}}, "boundingBox": {"vertices": [{"x": 301, "y": 242}, {"x": 302, "y": 242}, {"x": 302, "y": 251}, {"x": 301, "y": 251}]}, "text": "O"}]}]}], "blockType": "TEXT"}, {"property": {"detectedLanguages": [{"languageCode": "da", "confidence": 1.0}]}, "boundingBox": {"vertices": [{"x": 317, "y": 240}, {"x": 345, "y": 239}, {"x": 345, "y": 249}, {"x": 317, "y": 250}]}, "paragraphs": [{"property": {"detectedLanguages": [{"languageCode": "da", "confidence": 1.0}]}, "boundingBox": {"vertices": [{"x": 317, "y": 240}, {"x": 345, "y": 239}, {"x": 345, "y": 249}, {"x": 317, "y": 250}]}, "words": [{"property": {"detectedLanguages": [{"languageCode": "da"}]}, "boundingBox": {"vertices": [{"x": 317, "y": 241}, {"x": 335, "y": 241}, {"x": 335, "y": 250}, {"x": 317, "y": 250}]}, "symbols": [{"property": {"detectedLanguages": [{"languageCode": "da"}]}, "boundingBox": {"vertices": [{"x": 317, "y": 241}, {"x": 323, "y": 241}, {"x": 323, "y": 250}, {"x": 317, "y": 250}]}, "text": "M"}, {"property": {"detectedLanguages": [{"languageCode": "da"}]}, "boundingBox": {"vertices": [{"x": 324, "y": 241}, {"x": 325, "y": 241}, {"x": 325, "y": 250}, {"x": 324, "y": 250}]}, "text": "I"}, {"property": {"detectedLanguages": [{"languageCode": "da"}]}, "boundingBox": {"vertices": [{"x": 326, "y": 241}, {"x": 328, "y": 241}, {"x": 328, "y": 250}, {"x": 326, "y": 250}]}, "text": "C"}, {"property": {"detectedLanguages": [{"languageCode": "da"}]}, "boundingBox": {"vertices": [{"x": 329, "y": 241}, {"x": 332, "y": 241}, {"x": 332, "y": 250}, {"x": 329, "y": 250}]}, "text": "R"}, {"property": {"detectedLanguages": [{"languageCode": "da"}], "detectedBreak": {"type": "SPACE"}}, "boundingBox": {"vertices": [{"x": 333, "y": 241}, {"x": 335, "y": 241}, {"x": 335, "y": 250}, {"x": 333, "y": 250}]}, "text": "O"}]}, {"property": {"detectedLanguages": [{"languageCode": "da"}]}, "boundingBox": {"vertices": [{"x": 337, "y": 240}, {"x": 345, "y": 240}, {"x": 345, "y": 250}, {"x": 337, "y": 250}]}, "symbols": [{"property": {"detectedLanguages": [{"languageCode": "da"}]}, "boundingBox": {"vertices": [{"x": 337, "y": 241}, {"x": 340, "y": 241}, {"x": 340, "y": 250}, {"x": 337, "y": 250}]}, "text": "F"}, {"property": {"detectedLanguages": [{"languageCode": "da"}]}, "boundingBox": {"vertices": [{"x": 341, "y": 240}, {"x": 342, "y": 240}, {"x": 342, "y": 249}, {"x": 341, "y": 249}]}, "text": "R"}, {"property": {"detectedLanguages": [{"languageCode": "da"}], "detectedBreak": {"type": "LINE_BREAK"}}, "boundingBox": {"vertices": [{"x": 343, "y": 240}, {"x": 345, "y": 240}, {"x": 345, "y": 249}, {"x": 343, "y": 249}]}, "text": "I"}]}]}], "blockType": "TEXT"}, {"property": {"detectedLanguages": [{"languageCode": "ca", "confidence": 1.0}]}, "boundingBox": {"vertices": [{"x": 300, "y": 250}, {"x": 348, "y": 249}, {"x": 348, "y": 259}, {"x": 300, "y": 260}]}, "paragraphs": [{"property": {"detectedLanguages": [{"languageCode": "ca", "confidence": 1.0}]}, "boundingBox": {"vertices": [{"x": 300, "y": 250}, {"x": 348, "y": 249}, {"x": 348, "y": 259}, {"x": 300, "y": 260}]}, "words": [{"property": {"detectedLanguages": [{"languageCode": "ca"}]}, "boundingBox": {"vertices": [{"x": 300, "y": 251}, {"x": 319, "y": 251}, {"x": 319, "y": 258}, {"x": 300, "y": 258}]}, "symbols": [{"property": {"detectedLanguages": [{"languageCode": "ca"}]}, "boundingBox": {"vertices": [{"x": 300, "y": 251}, {"x": 306, "y": 251}, {"x": 306, "y": 258}, {"x": 300, "y": 258}]}, "text": "C"}, {"property": {"detectedLanguages": [{"languageCode": "ca"}]}, "boundingBox": {"vertices": [{"x": 307, "y": 251}, {"x": 307, "y": 251}, {"x": 307, "y": 258}, {"x": 307, "y": 258}]}, "text": "O"}, {"property": {"detectedLanguages": [{"languageCode": "ca"}]}, "boundingBox": {"vertices": [{"x": 308, "y": 251}, {"x": 309, "y": 251}, {"x": 309, "y": 258}, {"x": 308, "y": 258}]}, "text": "F"}, {"property": {"detectedLanguages": [{"languageCode": "ca"}]}, "boundingBox": {"vertices": [{"x": 310, "y": 251}, {"x": 315, "y": 251}, {"x": 315, "y": 258}, {"x": 310, "y": 258}]}, "text": "F"}, {"property": {"detectedLanguages": [{"languageCode": "ca"}]}, "boundingBox": {"vertices": [{"x": 316, "y": 251}, {"x": 317, "y": 251}, {"x": 317, "y": 258}, {"x": 316, "y": 258}]}, "text": "E"}, {"property": {"detectedLanguages": [{"languageCode": "ca"}], "detectedBreak": {"type": "SPACE"}}, "boundingBox": {"vertices": [{"x": 318, "y": 251}, {"x": 319, "y": 251}, {"x": 319, "y": 258}, {"x": 318, "y": 258}]}, "text": "E"}]}, {"property": {"detectedLanguages": [{"languageCode": "ca"}]}, "boundingBox": {"vertices": [{"x": 326, "y": 249}, {"x": 348, "y": 248}, {"x": 348, "y": 258}, {"x": 326, "y": 259}]}, "symbols": [{"property": {"detectedLanguages": [{"languageCode": "ca"}]}, "boundingBox": {"vertices": [{"x": 326, "y": 249}, {"x": 329, "y": 249}, {"x": 329, "y": 259}, {"x": 326, "y": 259}]}, "text": "E"}, {"property": {"detectedLanguages": [{"languageCode": "ca"}]}, "boundingBox": {"vertices": [{"x": 330, "y": 249}, {"x": 333, "y": 249}, {"x": 333, "y": 259}, {"x": 330, "y": 259}]}, "text": "L"}, {"property": {"detectedLanguages": [{"languageCode": "ca"}]}, "boundingBox": {"vertices": [{"x": 334, "y": 249}, {"x": 335, "y": 249}, {"x": 335, "y": 259}, {"x": 334, "y": 259}]}, "text": "E"}, {"property": {"detectedLanguages": [{"languageCode": "ca"}]}, "boundingBox": {"vertices": [{"x": 336, "y": 249}, {"x": 339, "y": 249}, {"x": 339, "y": 259}, {"x": 336, "y": 259}]}, "text": "V"}, {"property": {"detectedLanguages": [{"languageCode": "ca"}]}, "boundingBox": {"vertices": [{"x": 340, "y": 249}, {"x": 342, "y": 249}, {"x": 342, "y": 259}, {"x": 340, "y": 259}]}, "text": "A"}, {"property": {"detectedLanguages": [{"languageCode": "ca"}], "detectedBreak": {"type": "LINE_BREAK"}}, "boundingBox": {"vertices": [{"x": 343, "y": 249}, {"x": 348, "y": 249}, {"x": 348, "y": 259}, {"x": 343, "y": 259}]}, "text": "T"}]}]}], "blockType": "TEXT"}, {"boundingBox": {"vertices": [{"x": 353, "y": 217}, {"x": 354, "y": 245}, {"x": 345, "y": 245}, {"x": 344, "y": 217}]}, "paragraphs": [{"boundingBox": {"vertices": [{"x": 353, "y": 217}, {"x": 354, "y": 245}, {"x": 345, "y": 245}, {"x": 344, "y": 217}]}, "words": [{"boundingBox": {"vertices": [{"x": 353, "y": 217}, {"x": 354, "y": 245}, {"x": 345, "y": 245}, {"x": 344, "y": 217}]}, "symbols": [{"property": {"detectedBreak": {"type": "LINE_BREAK"}}, "boundingBox": {"vertices": [{"x": 353, "y": 217}, {"x": 354, "y": 245}, {"x": 345, "y": 245}, {"x": 344, "y": 217}]}, "text": "\u3057"}]}]}], "blockType": "TEXT"}, {"boundingBox": {"vertices": [{"x": 121, "y": 267}, {"x": 121, "y": 279}, {"x": 111, "y": 279}, {"x": 110, "y": 267}]}, "paragraphs": [{"boundingBox": {"vertices": [{"x": 121, "y": 267}, {"x": 121, "y": 279}, {"x": 111, "y": 279}, {"x": 110, "y": 267}]}, "words": [{"boundingBox": {"vertices": [{"x": 121, "y": 267}, {"x": 121, "y": 279}, {"x": 111, "y": 279}, {"x": 110, "y": 267}]}, "symbols": [{"boundingBox": {"vertices": [{"x": 120, "y": 267}, {"x": 120, "y": 277}, {"x": 110, "y": 277}, {"x": 110, "y": 267}]}, "text": "6"}, {"property": {"detectedBreak": {"type": "LINE_BREAK"}}, "boundingBox": {"vertices": [{"x": 121, "y": 278}, {"x": 121, "y": 279}, {"x": 111, "y": 279}, {"x": 111, "y": 278}]}, "text": "9"}]}]}], "blockType": "TEXT"}]}], "text": "PIGEON FORGE\nMOTOR LODGE\nHACARCY\nKING OUEEN EDS\nAMERICAN\nFAMLY ONNED\nWATER MOS\n15\n-1come\nFREE\nPANCAKE BREAKFASTI\nHBO\nMICRO FRI\nCOFFEE ELEVAT\n\u3057\n69\n"}}