{"textAnnotations": [{"locale": "en", "description": "R\nLUCKY LIQUOR\nPHON\nATM\nATM\nLA\nKDL\n", "boundingPoly": {"vertices": [{"x": 37, "y": 83}, {"x": 325, "y": 83}, {"x": 325, "y": 346}, {"x": 37, "y": 346}]}}, {"description": "R", "boundingPoly": {"vertices": [{"x": 131, "y": 83}, {"x": 163, "y": 87}, {"x": 159, "y": 120}, {"x": 127, "y": 116}]}}, {"description": "LUCKY", "boundingPoly": {"vertices": [{"x": 37, "y": 154}, {"x": 122, "y": 130}, {"x": 139, "y": 192}, {"x": 54, "y": 216}]}}, {"description": "LIQUOR", "boundingPoly": {"vertices": [{"x": 136, "y": 127}, {"x": 255, "y": 93}, {"x": 273, "y": 155}, {"x": 153, "y": 189}]}}, {"description": "PHON", "boundingPoly": {"vertices": [{"x": 263, "y": 201}, {"x": 278, "y": 201}, {"x": 278, "y": 208}, {"x": 263, "y": 208}]}}, {"description": "ATM", "boundingPoly": {"vertices": [{"x": 262, "y": 226}, {"x": 280, "y": 226}, {"x": 280, "y": 236}, {"x": 262, "y": 236}]}}, {"description": "ATM", "boundingPoly": {"vertices": [{"x": 183, "y": 290}, {"x": 225, "y": 290}, {"x": 225, "y": 315}, {"x": 183, "y": 315}]}}, {"description": "LA", "boundingPoly": {"vertices": [{"x": 312, "y": 321}, {"x": 325, "y": 321}, {"x": 325, "y": 330}, {"x": 312, "y": 330}]}}, {"description": "KDL", "boundingPoly": {"vertices": [{"x": 241, "y": 337}, {"x": 255, "y": 338}, {"x": 254, "y": 346}, {"x": 240, "y": 345}]}}], "fullTextAnnotation": {"pages": [{"property": {"detectedLanguages": [{"languageCode": "en", "confidence": 0.41}]}, "width": 500, "height": 375, "blocks": [{"boundingBox": {"vertices": [{"x": 131, "y": 83}, {"x": 163, "y": 87}, {"x": 159, "y": 120}, {"x": 127, "y": 116}]}, "paragraphs": [{"boundingBox": {"vertices": [{"x": 131, "y": 83}, {"x": 163, "y": 87}, {"x": 159, "y": 120}, {"x": 127, "y": 116}]}, "words": [{"boundingBox": {"vertices": [{"x": 131, "y": 83}, {"x": 163, "y": 87}, {"x": 159, "y": 120}, {"x": 127, "y": 116}]}, "symbols": [{"property": {"detectedBreak": {"type": "LINE_BREAK"}}, "boundingBox": {"vertices": [{"x": 131, "y": 83}, {"x": 163, "y": 87}, {"x": 159, "y": 120}, {"x": 127, "y": 116}]}, "text": "R"}]}]}], "blockType": "TEXT"}, {"property": {"detectedLanguages": [{"languageCode": "en", "confidence": 1.0}]}, "boundingBox": {"vertices": [{"x": 37, "y": 154}, {"x": 255, "y": 92}, {"x": 273, "y": 155}, {"x": 55, "y": 217}]}, "paragraphs": [{"property": {"detectedLanguages": [{"languageCode": "en", "confidence": 1.0}]}, "boundingBox": {"vertices": [{"x": 37, "y": 154}, {"x": 255, "y": 92}, {"x": 273, "y": 155}, {"x": 55, "y": 217}]}, "words": [{"property": {"detectedLanguages": [{"languageCode": "en"}]}, "boundingBox": {"vertices": [{"x": 37, "y": 154}, {"x": 122, "y": 130}, {"x": 139, "y": 192}, {"x": 54, "y": 216}]}, "symbols": [{"property": {"detectedLanguages": [{"languageCode": "en"}]}, "boundingBox": {"vertices": [{"x": 37, "y": 154}, {"x": 70, "y": 145}, {"x": 87, "y": 205}, {"x": 54, "y": 215}]}, "text": "L"}, {"property": {"detectedLanguages": [{"languageCode": "en"}]}, "boundingBox": {"vertices": [{"x": 71, "y": 145}, {"x": 80, "y": 143}, {"x": 97, "y": 203}, {"x": 88, "y": 206}]}, "text": "U"}, {"property": {"detectedLanguages": [{"languageCode": "en"}]}, "boundingBox": {"vertices": [{"x": 81, "y": 142}, {"x": 92, "y": 139}, {"x": 109, "y": 200}, {"x": 98, "y": 203}]}, "text": "C"}, {"property": {"detectedLanguages": [{"languageCode": "en"}]}, "boundingBox": {"vertices": [{"x": 92, "y": 139}, {"x": 110, "y": 134}, {"x": 127, "y": 194}, {"x": 109, "y": 200}]}, "text": "K"}, {"property": {"detectedLanguages": [{"languageCode": "en"}], "detectedBreak": {"type": "SPACE"}}, "boundingBox": {"vertices": [{"x": 111, "y": 133}, {"x": 122, "y": 130}, {"x": 139, "y": 191}, {"x": 128, "y": 194}]}, "text": "Y"}]}, {"property": {"detectedLanguages": [{"languageCode": "en"}]}, "boundingBox": {"vertices": [{"x": 136, "y": 127}, {"x": 255, "y": 93}, {"x": 273, "y": 155}, {"x": 153, "y": 189}]}, "symbols": [{"property": {"detectedLanguages": [{"languageCode": "en"}]}, "boundingBox": {"vertices": [{"x": 136, "y": 128}, {"x": 173, "y": 118}, {"x": 190, "y": 178}, {"x": 153, "y": 189}]}, "text": "L"}, {"property": {"detectedLanguages": [{"languageCode": "en"}]}, "boundingBox": {"vertices": [{"x": 173, "y": 117}, {"x": 184, "y": 114}, {"x": 201, "y": 175}, {"x": 190, "y": 178}]}, "text": "I"}, {"property": {"detectedLanguages": [{"languageCode": "en"}]}, "boundingBox": {"vertices": [{"x": 185, "y": 114}, {"x": 203, "y": 109}, {"x": 220, "y": 169}, {"x": 202, "y": 175}]}, "text": "Q"}, {"property": {"detectedLanguages": [{"languageCode": "en"}]}, "boundingBox": {"vertices": [{"x": 204, "y": 108}, {"x": 215, "y": 105}, {"x": 232, "y": 166}, {"x": 221, "y": 169}]}, "text": "U"}, {"property": {"detectedLanguages": [{"languageCode": "en"}]}, "boundingBox": {"vertices": [{"x": 216, "y": 105}, {"x": 234, "y": 100}, {"x": 251, "y": 160}, {"x": 233, "y": 166}]}, "text": "O"}, {"property": {"detectedLanguages": [{"languageCode": "en"}], "detectedBreak": {"type": "LINE_BREAK"}}, "boundingBox": {"vertices": [{"x": 235, "y": 100}, {"x": 255, "y": 94}, {"x": 272, "y": 155}, {"x": 252, "y": 161}]}, "text": "R"}]}]}], "blockType": "TEXT"}, {"boundingBox": {"vertices": [{"x": 263, "y": 201}, {"x": 278, "y": 201}, {"x": 278, "y": 208}, {"x": 263, "y": 208}]}, "paragraphs": [{"boundingBox": {"vertices": [{"x": 263, "y": 201}, {"x": 278, "y": 201}, {"x": 278, "y": 208}, {"x": 263, "y": 208}]}, "words": [{"boundingBox": {"vertices": [{"x": 263, "y": 201}, {"x": 278, "y": 201}, {"x": 278, "y": 208}, {"x": 263, "y": 208}]}, "symbols": [{"boundingBox": {"vertices": [{"x": 263, "y": 201}, {"x": 268, "y": 201}, {"x": 268, "y": 208}, {"x": 263, "y": 208}]}, "text": "P"}, {"boundingBox": {"vertices": [{"x": 269, "y": 201}, {"x": 272, "y": 201}, {"x": 272, "y": 208}, {"x": 269, "y": 208}]}, "text": "H"}, {"boundingBox": {"vertices": [{"x": 273, "y": 201}, {"x": 275, "y": 201}, {"x": 275, "y": 208}, {"x": 273, "y": 208}]}, "text": "O"}, {"property": {"detectedBreak": {"type": "LINE_BREAK"}}, "boundingBox": {"vertices": [{"x": 276, "y": 201}, {"x": 278, "y": 201}, {"x": 278, "y": 208}, {"x": 276, "y": 208}]}, "text": "N"}]}]}], "blockType": "TEXT"}, {"boundingBox": {"vertices": [{"x": 262, "y": 226}, {"x": 280, "y": 226}, {"x": 280, "y": 236}, {"x": 262, "y": 236}]}, "paragraphs": [{"boundingBox": {"vertices": [{"x": 262, "y": 226}, {"x": 280, "y": 226}, {"x": 280, "y": 236}, {"x": 262, "y": 236}]}, "words": [{"boundingBox": {"vertices": [{"x": 262, "y": 226}, {"x": 280, "y": 226}, {"x": 280, "y": 236}, {"x": 262, "y": 236}]}, "symbols": [{"boundingBox": {"vertices": [{"x": 262, "y": 226}, {"x": 271, "y": 226}, {"x": 271, "y": 236}, {"x": 262, "y": 236}]}, "text": "A"}, {"boundingBox": {"vertices": [{"x": 272, "y": 226}, {"x": 274, "y": 226}, {"x": 274, "y": 236}, {"x": 272, "y": 236}]}, "text": "T"}, {"property": {"detectedBreak": {"type": "LINE_BREAK"}}, "boundingBox": {"vertices": [{"x": 275, "y": 226}, {"x": 280, "y": 226}, {"x": 280, "y": 236}, {"x": 275, "y": 236}]}, "text": "M"}]}]}], "blockType": "TEXT"}, {"boundingBox": {"vertices": [{"x": 183, "y": 290}, {"x": 225, "y": 290}, {"x": 225, "y": 315}, {"x": 183, "y": 315}]}, "paragraphs": [{"boundingBox": {"vertices": [{"x": 183, "y": 290}, {"x": 225, "y": 290}, {"x": 225, "y": 315}, {"x": 183, "y": 315}]}, "words": [{"boundingBox": {"vertices": [{"x": 183, "y": 290}, {"x": 225, "y": 290}, {"x": 225, "y": 315}, {"x": 183, "y": 315}]}, "symbols": [{"boundingBox": {"vertices": [{"x": 183, "y": 290}, {"x": 203, "y": 290}, {"x": 203, "y": 315}, {"x": 183, "y": 315}]}, "text": "A"}, {"boundingBox": {"vertices": [{"x": 204, "y": 290}, {"x": 212, "y": 290}, {"x": 212, "y": 315}, {"x": 204, "y": 315}]}, "text": "T"}, {"property": {"detectedBreak": {"type": "LINE_BREAK"}}, "boundingBox": {"vertices": [{"x": 213, "y": 290}, {"x": 225, "y": 290}, {"x": 225, "y": 315}, {"x": 213, "y": 315}]}, "text": "M"}]}]}], "blockType": "TEXT"}, {"boundingBox": {"vertices": [{"x": 312, "y": 321}, {"x": 325, "y": 321}, {"x": 325, "y": 330}, {"x": 312, "y": 330}]}, "paragraphs": [{"boundingBox": {"vertices": [{"x": 312, "y": 321}, {"x": 325, "y": 321}, {"x": 325, "y": 330}, {"x": 312, "y": 330}]}, "words": [{"boundingBox": {"vertices": [{"x": 312, "y": 321}, {"x": 325, "y": 321}, {"x": 325, "y": 330}, {"x": 312, "y": 330}]}, "symbols": [{"boundingBox": {"vertices": [{"x": 312, "y": 321}, {"x": 317, "y": 321}, {"x": 317, "y": 328}, {"x": 312, "y": 328}]}, "text": "L"}, {"property": {"detectedBreak": {"type": "LINE_BREAK"}}, "boundingBox": {"vertices": [{"x": 319, "y": 322}, {"x": 325, "y": 322}, {"x": 325, "y": 330}, {"x": 319, "y": 330}]}, "text": "A"}]}]}], "blockType": "TEXT"}, {"boundingBox": {"vertices": [{"x": 241, "y": 337}, {"x": 255, "y": 338}, {"x": 254, "y": 346}, {"x": 240, "y": 345}]}, "paragraphs": [{"boundingBox": {"vertices": [{"x": 241, "y": 337}, {"x": 255, "y": 338}, {"x": 254, "y": 346}, {"x": 240, "y": 345}]}, "words": [{"boundingBox": {"vertices": [{"x": 241, "y": 337}, {"x": 255, "y": 338}, {"x": 254, "y": 346}, {"x": 240, "y": 345}]}, "symbols": [{"boundingBox": {"vertices": [{"x": 241, "y": 337}, {"x": 246, "y": 337}, {"x": 245, "y": 344}, {"x": 241, "y": 344}]}, "text": "K"}, {"boundingBox": {"vertices": [{"x": 247, "y": 338}, {"x": 253, "y": 338}, {"x": 252, "y": 345}, {"x": 247, "y": 345}]}, "text": "D"}, {"property": {"detectedBreak": {"type": "LINE_BREAK"}}, "boundingBox": {"vertices": [{"x": 254, "y": 338}, {"x": 255, "y": 338}, {"x": 254, "y": 345}, {"x": 254, "y": 345}]}, "text": "L"}]}]}], "blockType": "TEXT"}]}], "text": "R\nLUCKY LIQUOR\nPHON\nATM\nATM\nLA\nKDL\n"}}