{"textAnnotations": [{"locale": "en", "description": "RSM\nLouis' Steah Trse\n", "boundingPoly": {"vertices": [{"x": 42, "y": 102}, {"x": 374, "y": 102}, {"x": 374, "y": 191}, {"x": 42, "y": 191}]}}, {"description": "RSM", "boundingPoly": {"vertices": [{"x": 44, "y": 102}, {"x": 67, "y": 105}, {"x": 65, "y": 121}, {"x": 42, "y": 118}]}}, {"description": "Louis'", "boundingPoly": {"vertices": [{"x": 124, "y": 115}, {"x": 249, "y": 125}, {"x": 244, "y": 181}, {"x": 120, "y": 172}]}}, {"description": "Steah", "boundingPoly": {"vertices": [{"x": 251, "y": 125}, {"x": 316, "y": 130}, {"x": 311, "y": 186}, {"x": 247, "y": 181}]}}, {"description": "Trse", "boundingPoly": {"vertices": [{"x": 318, "y": 130}, {"x": 374, "y": 134}, {"x": 369, "y": 191}, {"x": 314, "y": 187}]}}], "fullTextAnnotation": {"pages": [{"property": {"detectedLanguages": [{"languageCode": "en", "confidence": 0.83}]}, "width": 500, "height": 333, "blocks": [{"boundingBox": {"vertices": [{"x": 44, "y": 102}, {"x": 67, "y": 105}, {"x": 65, "y": 121}, {"x": 42, "y": 118}]}, "paragraphs": [{"boundingBox": {"vertices": [{"x": 44, "y": 102}, {"x": 67, "y": 105}, {"x": 65, "y": 121}, {"x": 42, "y": 118}]}, "words": [{"boundingBox": {"vertices": [{"x": 44, "y": 102}, {"x": 67, "y": 105}, {"x": 65, "y": 121}, {"x": 42, "y": 118}]}, "symbols": [{"boundingBox": {"vertices": [{"x": 44, "y": 103}, {"x": 56, "y": 105}, {"x": 54, "y": 119}, {"x": 42, "y": 118}]}, "text": "R"}, {"boundingBox": {"vertices": [{"x": 57, "y": 104}, {"x": 61, "y": 105}, {"x": 59, "y": 119}, {"x": 55, "y": 119}]}, "text": "S"}, {"property": {"detectedBreak": {"type": "LINE_BREAK"}}, "boundingBox": {"vertices": [{"x": 62, "y": 105}, {"x": 67, "y": 106}, {"x": 65, "y": 121}, {"x": 60, "y": 120}]}, "text": "M"}]}]}], "blockType": "TEXT"}, {"property": {"detectedLanguages": [{"languageCode": "en", "confidence": 1.0}]}, "boundingBox": {"vertices": [{"x": 124, "y": 115}, {"x": 374, "y": 134}, {"x": 370, "y": 191}, {"x": 120, "y": 172}]}, "paragraphs": [{"property": {"detectedLanguages": [{"languageCode": "en", "confidence": 1.0}]}, "boundingBox": {"vertices": [{"x": 124, "y": 115}, {"x": 374, "y": 134}, {"x": 370, "y": 191}, {"x": 120, "y": 172}]}, "words": [{"property": {"detectedLanguages": [{"languageCode": "en"}]}, "boundingBox": {"vertices": [{"x": 124, "y": 115}, {"x": 249, "y": 125}, {"x": 244, "y": 181}, {"x": 120, "y": 172}]}, "symbols": [{"property": {"detectedLanguages": [{"languageCode": "en"}]}, "boundingBox": {"vertices": [{"x": 124, "y": 115}, {"x": 162, "y": 118}, {"x": 158, "y": 174}, {"x": 120, "y": 171}]}, "text": "L"}, {"property": {"detectedLanguages": [{"languageCode": "en"}]}, "boundingBox": {"vertices": [{"x": 163, "y": 118}, {"x": 181, "y": 119}, {"x": 177, "y": 175}, {"x": 159, "y": 174}]}, "text": "o"}, {"property": {"detectedLanguages": [{"languageCode": "en"}]}, "boundingBox": {"vertices": [{"x": 182, "y": 120}, {"x": 210, "y": 122}, {"x": 206, "y": 178}, {"x": 178, "y": 176}]}, "text": "u"}, {"property": {"detectedLanguages": [{"languageCode": "en"}]}, "boundingBox": {"vertices": [{"x": 211, "y": 122}, {"x": 220, "y": 123}, {"x": 216, "y": 179}, {"x": 207, "y": 178}]}, "text": "i"}, {"property": {"detectedLanguages": [{"languageCode": "en"}]}, "boundingBox": {"vertices": [{"x": 221, "y": 123}, {"x": 239, "y": 124}, {"x": 235, "y": 180}, {"x": 217, "y": 179}]}, "text": "s"}, {"property": {"detectedLanguages": [{"languageCode": "en"}], "detectedBreak": {"type": "SPACE"}}, "boundingBox": {"vertices": [{"x": 240, "y": 124}, {"x": 249, "y": 125}, {"x": 245, "y": 181}, {"x": 236, "y": 180}]}, "text": "'"}]}, {"property": {"detectedLanguages": [{"languageCode": "en"}]}, "boundingBox": {"vertices": [{"x": 251, "y": 125}, {"x": 316, "y": 130}, {"x": 311, "y": 186}, {"x": 247, "y": 181}]}, "symbols": [{"property": {"detectedLanguages": [{"languageCode": "en"}]}, "boundingBox": {"vertices": [{"x": 251, "y": 125}, {"x": 268, "y": 126}, {"x": 264, "y": 182}, {"x": 247, "y": 181}]}, "text": "S"}, {"property": {"detectedLanguages": [{"languageCode": "en"}]}, "boundingBox": {"vertices": [{"x": 269, "y": 126}, {"x": 278, "y": 127}, {"x": 274, "y": 183}, {"x": 265, "y": 182}]}, "text": "t"}, {"property": {"detectedLanguages": [{"languageCode": "en"}]}, "boundingBox": {"vertices": [{"x": 279, "y": 127}, {"x": 288, "y": 128}, {"x": 284, "y": 184}, {"x": 275, "y": 183}]}, "text": "e"}, {"property": {"detectedLanguages": [{"languageCode": "en"}]}, "boundingBox": {"vertices": [{"x": 288, "y": 128}, {"x": 296, "y": 129}, {"x": 292, "y": 184}, {"x": 284, "y": 184}]}, "text": "a"}, {"property": {"detectedLanguages": [{"languageCode": "en"}], "detectedBreak": {"type": "SPACE"}}, "boundingBox": {"vertices": [{"x": 297, "y": 129}, {"x": 316, "y": 130}, {"x": 312, "y": 186}, {"x": 293, "y": 185}]}, "text": "h"}]}, {"property": {"detectedLanguages": [{"languageCode": "en"}]}, "boundingBox": {"vertices": [{"x": 318, "y": 130}, {"x": 374, "y": 134}, {"x": 369, "y": 191}, {"x": 314, "y": 187}]}, "symbols": [{"property": {"detectedLanguages": [{"languageCode": "en"}]}, "boundingBox": {"vertices": [{"x": 318, "y": 130}, {"x": 335, "y": 131}, {"x": 331, "y": 187}, {"x": 314, "y": 186}]}, "text": "T"}, {"property": {"detectedLanguages": [{"languageCode": "en"}]}, "boundingBox": {"vertices": [{"x": 336, "y": 132}, {"x": 345, "y": 133}, {"x": 341, "y": 189}, {"x": 332, "y": 188}]}, "text": "r"}, {"property": {"detectedLanguages": [{"languageCode": "en"}]}, "boundingBox": {"vertices": [{"x": 346, "y": 132}, {"x": 364, "y": 133}, {"x": 360, "y": 189}, {"x": 342, "y": 188}]}, "text": "s"}, {"property": {"detectedLanguages": [{"languageCode": "en"}], "detectedBreak": {"type": "LINE_BREAK"}}, "boundingBox": {"vertices": [{"x": 365, "y": 134}, {"x": 374, "y": 135}, {"x": 370, "y": 191}, {"x": 361, "y": 190}]}, "text": "e"}]}]}], "blockType": "TEXT"}]}], "text": "RSM\nLouis' Steah Trse\n"}}