{"textAnnotations": [{"locale": "en", "description": "MONEY\nLOAN\n-10-\nBARBER SALON\nDIAMOND\nJEWELRY\nCASA\nE EMPENO\n709\nTOOUS\nUS JUZGADOS\nEND DE CRISTO\nSTRAS OBRAS\nSMAI AS\nMONEY TO LOAN\nASA DE EMPE\u00d1O\nUNIO\nJE\nGUN\n711\nJESUS\nEXCELENTESPRESTAMS\nIS\n\u00b7FANES\nSLAI TOP\nLORD\n", "boundingPoly": {"vertices": [{"x": 1, "y": 37}, {"x": 499, "y": 37}, {"x": 499, "y": 284}, {"x": 1, "y": 284}]}}, {"description": "MONEY", "boundingPoly": {"vertices": [{"x": 451, "y": 45}, {"x": 486, "y": 37}, {"x": 490, "y": 53}, {"x": 454, "y": 61}]}}, {"description": "LOAN", "boundingPoly": {"vertices": [{"x": 450, "y": 66}, {"x": 484, "y": 60}, {"x": 486, "y": 76}, {"x": 453, "y": 82}]}}, {"description": "-10-", "boundingPoly": {"vertices": [{"x": 455, "y": 60}, {"x": 484, "y": 53}, {"x": 485, "y": 58}, {"x": 456, "y": 65}]}}, {"description": "BARBER", "boundingPoly": {"vertices": [{"x": 193, "y": 93}, {"x": 240, "y": 101}, {"x": 238, "y": 112}, {"x": 191, "y": 104}]}}, {"description": "SALON", "boundingPoly": {"vertices": [{"x": 248, "y": 104}, {"x": 277, "y": 109}, {"x": 275, "y": 119}, {"x": 246, "y": 114}]}}, {"description": "DIAMOND", "boundingPoly": {"vertices": [{"x": 448, "y": 84}, {"x": 481, "y": 77}, {"x": 484, "y": 89}, {"x": 450, "y": 96}]}}, {"description": "JEWELRY", "boundingPoly": {"vertices": [{"x": 449, "y": 97}, {"x": 483, "y": 90}, {"x": 486, "y": 102}, {"x": 451, "y": 109}]}}, {"description": "CASA", "boundingPoly": {"vertices": [{"x": 461, "y": 110}, {"x": 474, "y": 108}, {"x": 475, "y": 115}, {"x": 462, "y": 117}]}}, {"description": "E", "boundingPoly": {"vertices": [{"x": 456, "y": 120}, {"x": 461, "y": 119}, {"x": 463, "y": 129}, {"x": 458, "y": 130}]}}, {"description": "EMPENO", "boundingPoly": {"vertices": [{"x": 463, "y": 119}, {"x": 481, "y": 116}, {"x": 483, "y": 127}, {"x": 465, "y": 130}]}}, {"description": "709", "boundingPoly": {"vertices": [{"x": 462, "y": 130}, {"x": 475, "y": 129}, {"x": 476, "y": 136}, {"x": 463, "y": 137}]}}, {"description": "TOOUS", "boundingPoly": {"vertices": [{"x": 13, "y": 182}, {"x": 61, "y": 174}, {"x": 64, "y": 189}, {"x": 15, "y": 197}]}}, {"description": "US", "boundingPoly": {"vertices": [{"x": 1, "y": 199}, {"x": 11, "y": 198}, {"x": 12, "y": 211}, {"x": 3, "y": 212}]}}, {"description": "JUZGADOS", "boundingPoly": {"vertices": [{"x": 12, "y": 197}, {"x": 66, "y": 191}, {"x": 67, "y": 205}, {"x": 14, "y": 211}]}}, {"description": "END", "boundingPoly": {"vertices": [{"x": 1, "y": 211}, {"x": 13, "y": 210}, {"x": 14, "y": 224}, {"x": 2, "y": 225}]}}, {"description": "DE", "boundingPoly": {"vertices": [{"x": 13, "y": 213}, {"x": 23, "y": 212}, {"x": 24, "y": 220}, {"x": 14, "y": 221}]}}, {"description": "CRISTO", "boundingPoly": {"vertices": [{"x": 25, "y": 210}, {"x": 65, "y": 207}, {"x": 66, "y": 220}, {"x": 26, "y": 223}]}}, {"description": "STRAS", "boundingPoly": {"vertices": [{"x": 1, "y": 223}, {"x": 25, "y": 223}, {"x": 25, "y": 236}, {"x": 1, "y": 236}]}}, {"description": "OBRAS", "boundingPoly": {"vertices": [{"x": 27, "y": 222}, {"x": 60, "y": 222}, {"x": 60, "y": 236}, {"x": 27, "y": 236}]}}, {"description": "SMAI", "boundingPoly": {"vertices": [{"x": 20, "y": 238}, {"x": 40, "y": 239}, {"x": 40, "y": 250}, {"x": 20, "y": 249}]}}, {"description": "AS", "boundingPoly": {"vertices": [{"x": 44, "y": 238}, {"x": 56, "y": 238}, {"x": 56, "y": 249}, {"x": 44, "y": 249}]}}, {"description": "MONEY", "boundingPoly": {"vertices": [{"x": 354, "y": 153}, {"x": 407, "y": 160}, {"x": 404, "y": 177}, {"x": 352, "y": 170}]}}, {"description": "TO", "boundingPoly": {"vertices": [{"x": 414, "y": 162}, {"x": 429, "y": 164}, {"x": 427, "y": 178}, {"x": 412, "y": 176}]}}, {"description": "LOAN", "boundingPoly": {"vertices": [{"x": 435, "y": 163}, {"x": 464, "y": 167}, {"x": 461, "y": 185}, {"x": 433, "y": 181}]}}, {"description": "ASA", "boundingPoly": {"vertices": [{"x": 365, "y": 177}, {"x": 396, "y": 180}, {"x": 395, "y": 194}, {"x": 364, "y": 191}]}}, {"description": "DE", "boundingPoly": {"vertices": [{"x": 400, "y": 182}, {"x": 415, "y": 183}, {"x": 414, "y": 195}, {"x": 399, "y": 194}]}}, {"description": "EMPE\u00d1O", "boundingPoly": {"vertices": [{"x": 419, "y": 180}, {"x": 460, "y": 184}, {"x": 458, "y": 200}, {"x": 418, "y": 196}]}}, {"description": "UNIO", "boundingPoly": {"vertices": [{"x": 481, "y": 173}, {"x": 499, "y": 174}, {"x": 498, "y": 182}, {"x": 480, "y": 181}]}}, {"description": "JE", "boundingPoly": {"vertices": [{"x": 491, "y": 188}, {"x": 499, "y": 189}, {"x": 498, "y": 197}, {"x": 490, "y": 196}]}}, {"description": "GUN", "boundingPoly": {"vertices": [{"x": 485, "y": 197}, {"x": 499, "y": 198}, {"x": 499, "y": 205}, {"x": 485, "y": 204}]}}, {"description": "711", "boundingPoly": {"vertices": [{"x": 240, "y": 202}, {"x": 251, "y": 202}, {"x": 251, "y": 207}, {"x": 240, "y": 207}]}}, {"description": "JESUS", "boundingPoly": {"vertices": [{"x": 129, "y": 214}, {"x": 187, "y": 216}, {"x": 186, "y": 235}, {"x": 128, "y": 233}]}}, {"description": "EXCELENTESPRESTAMS", "boundingPoly": {"vertices": [{"x": 362, "y": 216}, {"x": 470, "y": 220}, {"x": 470, "y": 229}, {"x": 362, "y": 225}]}}, {"description": "IS", "boundingPoly": {"vertices": [{"x": 147, "y": 241}, {"x": 164, "y": 241}, {"x": 164, "y": 257}, {"x": 147, "y": 257}]}}, {"description": "\u00b7FANES", "boundingPoly": {"vertices": [{"x": 272, "y": 240}, {"x": 286, "y": 240}, {"x": 286, "y": 245}, {"x": 272, "y": 245}]}}, {"description": "SLAI", "boundingPoly": {"vertices": [{"x": 272, "y": 246}, {"x": 284, "y": 246}, {"x": 284, "y": 252}, {"x": 272, "y": 252}]}}, {"description": "TOP", "boundingPoly": {"vertices": [{"x": 287, "y": 245}, {"x": 301, "y": 244}, {"x": 301, "y": 251}, {"x": 287, "y": 252}]}}, {"description": "LORD", "boundingPoly": {"vertices": [{"x": 126, "y": 265}, {"x": 178, "y": 265}, {"x": 178, "y": 284}, {"x": 126, "y": 284}]}}], "fullTextAnnotation": {"pages": [{"property": {"detectedLanguages": [{"languageCode": "en", "confidence": 0.38}, {"languageCode": "es", "confidence": 0.29}, {"languageCode": "pt", "confidence": 0.1}, {"languageCode": "fr", "confidence": 0.04}]}, "width": 500, "height": 375, "blocks": [{"property": {"detectedLanguages": [{"languageCode": "en", "confidence": 0.56}]}, "boundingBox": {"vertices": [{"x": 446, "y": 45}, {"x": 486, "y": 37}, {"x": 494, "y": 74}, {"x": 453, "y": 82}]}, "paragraphs": [{"property": {"detectedLanguages": [{"languageCode": "en", "confidence": 0.56}]}, "boundingBox": {"vertices": [{"x": 446, "y": 45}, {"x": 486, "y": 37}, {"x": 494, "y": 74}, {"x": 453, "y": 82}]}, "words": [{"property": {"detectedLanguages": [{"languageCode": "en"}]}, "boundingBox": {"vertices": [{"x": 451, "y": 45}, {"x": 486, "y": 37}, {"x": 490, "y": 53}, {"x": 454, "y": 61}]}, "symbols": [{"property": {"detectedLanguages": [{"languageCode": "en"}]}, "boundingBox": {"vertices": [{"x": 451, "y": 45}, {"x": 463, "y": 42}, {"x": 466, "y": 57}, {"x": 454, "y": 60}]}, "text": "M"}, {"property": {"detectedLanguages": [{"languageCode": "en"}]}, "boundingBox": {"vertices": [{"x": 464, "y": 43}, {"x": 471, "y": 41}, {"x": 474, "y": 56}, {"x": 467, "y": 58}]}, "text": "O"}, {"property": {"detectedLanguages": [{"languageCode": "en"}]}, "boundingBox": {"vertices": [{"x": 471, "y": 41}, {"x": 475, "y": 40}, {"x": 478, "y": 55}, {"x": 474, "y": 56}]}, "text": "N"}, {"property": {"detectedLanguages": [{"languageCode": "en"}]}, "boundingBox": {"vertices": [{"x": 476, "y": 40}, {"x": 480, "y": 39}, {"x": 483, "y": 54}, {"x": 479, "y": 55}]}, "text": "E"}, {"property": {"detectedLanguages": [{"languageCode": "en"}], "detectedBreak": {"type": "EOL_SURE_SPACE"}}, "boundingBox": {"vertices": [{"x": 481, "y": 39}, {"x": 486, "y": 38}, {"x": 489, "y": 53}, {"x": 484, "y": 54}]}, "text": "Y"}]}, {"boundingBox": {"vertices": [{"x": 450, "y": 66}, {"x": 484, "y": 60}, {"x": 486, "y": 76}, {"x": 453, "y": 82}]}, "symbols": [{"boundingBox": {"vertices": [{"x": 450, "y": 67}, {"x": 462, "y": 65}, {"x": 464, "y": 80}, {"x": 452, "y": 82}]}, "text": "L"}, {"boundingBox": {"vertices": [{"x": 463, "y": 65}, {"x": 470, "y": 64}, {"x": 472, "y": 79}, {"x": 465, "y": 80}]}, "text": "O"}, {"boundingBox": {"vertices": [{"x": 471, "y": 63}, {"x": 478, "y": 62}, {"x": 480, "y": 77}, {"x": 473, "y": 78}]}, "text": "A"}, {"property": {"detectedBreak": {"type": "LINE_BREAK"}}, "boundingBox": {"vertices": [{"x": 479, "y": 62}, {"x": 484, "y": 61}, {"x": 486, "y": 76}, {"x": 481, "y": 77}]}, "text": "N"}]}]}], "blockType": "TEXT"}, {"boundingBox": {"vertices": [{"x": 455, "y": 60}, {"x": 484, "y": 53}, {"x": 485, "y": 58}, {"x": 456, "y": 65}]}, "paragraphs": [{"boundingBox": {"vertices": [{"x": 455, "y": 60}, {"x": 484, "y": 53}, {"x": 485, "y": 58}, {"x": 456, "y": 65}]}, "words": [{"boundingBox": {"vertices": [{"x": 455, "y": 60}, {"x": 484, "y": 53}, {"x": 485, "y": 58}, {"x": 456, "y": 65}]}, "symbols": [{"boundingBox": {"vertices": [{"x": 455, "y": 60}, {"x": 466, "y": 58}, {"x": 467, "y": 62}, {"x": 456, "y": 65}]}, "text": "-"}, {"boundingBox": {"vertices": [{"x": 467, "y": 57}, {"x": 473, "y": 56}, {"x": 474, "y": 61}, {"x": 468, "y": 62}]}, "text": "1"}, {"boundingBox": {"vertices": [{"x": 474, "y": 56}, {"x": 478, "y": 55}, {"x": 479, "y": 60}, {"x": 475, "y": 61}]}, "text": "0"}, {"property": {"detectedBreak": {"type": "LINE_BREAK"}}, "boundingBox": {"vertices": [{"x": 479, "y": 55}, {"x": 484, "y": 54}, {"x": 485, "y": 59}, {"x": 480, "y": 60}]}, "text": "-"}]}]}], "blockType": "TEXT"}, {"property": {"detectedLanguages": [{"languageCode": "en", "confidence": 1.0}]}, "boundingBox": {"vertices": [{"x": 193, "y": 93}, {"x": 277, "y": 108}, {"x": 275, "y": 119}, {"x": 191, "y": 104}]}, "paragraphs": [{"property": {"detectedLanguages": [{"languageCode": "en", "confidence": 1.0}]}, "boundingBox": {"vertices": [{"x": 193, "y": 93}, {"x": 277, "y": 108}, {"x": 275, "y": 119}, {"x": 191, "y": 104}]}, "words": [{"property": {"detectedLanguages": [{"languageCode": "en"}]}, "boundingBox": {"vertices": [{"x": 193, "y": 93}, {"x": 240, "y": 101}, {"x": 238, "y": 112}, {"x": 191, "y": 104}]}, "symbols": [{"property": {"detectedLanguages": [{"languageCode": "en"}]}, "boundingBox": {"vertices": [{"x": 193, "y": 93}, {"x": 207, "y": 95}, {"x": 205, "y": 106}, {"x": 191, "y": 104}]}, "text": "B"}, {"property": {"detectedLanguages": [{"languageCode": "en"}]}, "boundingBox": {"vertices": [{"x": 208, "y": 96}, {"x": 216, "y": 97}, {"x": 214, "y": 108}, {"x": 206, "y": 107}]}, "text": "A"}, {"property": {"detectedLanguages": [{"languageCode": "en"}]}, "boundingBox": {"vertices": [{"x": 217, "y": 97}, {"x": 221, "y": 98}, {"x": 219, "y": 109}, {"x": 215, "y": 108}]}, "text": "R"}, {"property": {"detectedLanguages": [{"languageCode": "en"}]}, "boundingBox": {"vertices": [{"x": 223, "y": 98}, {"x": 229, "y": 99}, {"x": 227, "y": 110}, {"x": 221, "y": 109}]}, "text": "B"}, {"property": {"detectedLanguages": [{"languageCode": "en"}]}, "boundingBox": {"vertices": [{"x": 228, "y": 99}, {"x": 234, "y": 100}, {"x": 232, "y": 111}, {"x": 226, "y": 110}]}, "text": "E"}, {"property": {"detectedLanguages": [{"languageCode": "en"}], "detectedBreak": {"type": "SPACE"}}, "boundingBox": {"vertices": [{"x": 235, "y": 100}, {"x": 240, "y": 101}, {"x": 238, "y": 112}, {"x": 233, "y": 111}]}, "text": "R"}]}, {"property": {"detectedLanguages": [{"languageCode": "en"}]}, "boundingBox": {"vertices": [{"x": 248, "y": 104}, {"x": 277, "y": 109}, {"x": 275, "y": 119}, {"x": 246, "y": 114}]}, "symbols": [{"property": {"detectedLanguages": [{"languageCode": "en"}]}, "boundingBox": {"vertices": [{"x": 248, "y": 105}, {"x": 255, "y": 106}, {"x": 253, "y": 115}, {"x": 246, "y": 114}]}, "text": "S"}, {"property": {"detectedLanguages": [{"languageCode": "en"}]}, "boundingBox": {"vertices": [{"x": 256, "y": 106}, {"x": 262, "y": 107}, {"x": 260, "y": 116}, {"x": 254, "y": 115}]}, "text": "A"}, {"property": {"detectedLanguages": [{"languageCode": "en"}]}, "boundingBox": {"vertices": [{"x": 263, "y": 107}, {"x": 269, "y": 108}, {"x": 267, "y": 117}, {"x": 261, "y": 116}]}, "text": "L"}, {"property": {"detectedLanguages": [{"languageCode": "en"}]}, "boundingBox": {"vertices": [{"x": 269, "y": 108}, {"x": 272, "y": 109}, {"x": 270, "y": 117}, {"x": 267, "y": 117}]}, "text": "O"}, {"property": {"detectedLanguages": [{"languageCode": "en"}], "detectedBreak": {"type": "LINE_BREAK"}}, "boundingBox": {"vertices": [{"x": 273, "y": 109}, {"x": 277, "y": 110}, {"x": 275, "y": 119}, {"x": 271, "y": 118}]}, "text": "N"}]}]}], "blockType": "TEXT"}, {"property": {"detectedLanguages": [{"languageCode": "en", "confidence": 1.0}]}, "boundingBox": {"vertices": [{"x": 448, "y": 84}, {"x": 481, "y": 77}, {"x": 484, "y": 89}, {"x": 450, "y": 96}]}, "paragraphs": [{"property": {"detectedLanguages": [{"languageCode": "en", "confidence": 1.0}]}, "boundingBox": {"vertices": [{"x": 448, "y": 84}, {"x": 481, "y": 77}, {"x": 484, "y": 89}, {"x": 450, "y": 96}]}, "words": [{"property": {"detectedLanguages": [{"languageCode": "en"}]}, "boundingBox": {"vertices": [{"x": 448, "y": 84}, {"x": 481, "y": 77}, {"x": 484, "y": 89}, {"x": 450, "y": 96}]}, "symbols": [{"property": {"detectedLanguages": [{"languageCode": "en"}]}, "boundingBox": {"vertices": [{"x": 448, "y": 84}, {"x": 459, "y": 82}, {"x": 461, "y": 93}, {"x": 450, "y": 95}]}, "text": "D"}, {"property": {"detectedLanguages": [{"languageCode": "en"}]}, "boundingBox": {"vertices": [{"x": 460, "y": 82}, {"x": 461, "y": 82}, {"x": 463, "y": 93}, {"x": 462, "y": 93}]}, "text": "I"}, {"property": {"detectedLanguages": [{"languageCode": "en"}]}, "boundingBox": {"vertices": [{"x": 462, "y": 82}, {"x": 463, "y": 82}, {"x": 465, "y": 93}, {"x": 464, "y": 93}]}, "text": "A"}, {"property": {"detectedLanguages": [{"languageCode": "en"}]}, "boundingBox": {"vertices": [{"x": 464, "y": 82}, {"x": 471, "y": 81}, {"x": 473, "y": 91}, {"x": 466, "y": 93}]}, "text": "M"}, {"property": {"detectedLanguages": [{"languageCode": "en"}]}, "boundingBox": {"vertices": [{"x": 472, "y": 80}, {"x": 477, "y": 79}, {"x": 479, "y": 90}, {"x": 474, "y": 91}]}, "text": "O"}, {"property": {"detectedLanguages": [{"languageCode": "en"}]}, "boundingBox": {"vertices": [{"x": 477, "y": 79}, {"x": 480, "y": 78}, {"x": 482, "y": 89}, {"x": 479, "y": 90}]}, "text": "N"}, {"property": {"detectedLanguages": [{"languageCode": "en"}], "detectedBreak": {"type": "LINE_BREAK"}}, "boundingBox": {"vertices": [{"x": 481, "y": 78}, {"x": 481, "y": 78}, {"x": 483, "y": 89}, {"x": 483, "y": 89}]}, "text": "D"}]}]}], "blockType": "TEXT"}, {"property": {"detectedLanguages": [{"languageCode": "en", "confidence": 0.64}]}, "boundingBox": {"vertices": [{"x": 449, "y": 96}, {"x": 483, "y": 89}, {"x": 488, "y": 112}, {"x": 453, "y": 119}]}, "paragraphs": [{"property": {"detectedLanguages": [{"languageCode": "en", "confidence": 0.64}]}, "boundingBox": {"vertices": [{"x": 449, "y": 96}, {"x": 483, "y": 89}, {"x": 488, "y": 112}, {"x": 453, "y": 119}]}, "words": [{"property": {"detectedLanguages": [{"languageCode": "en"}]}, "boundingBox": {"vertices": [{"x": 449, "y": 97}, {"x": 483, "y": 90}, {"x": 486, "y": 102}, {"x": 451, "y": 109}]}, "symbols": [{"property": {"detectedLanguages": [{"languageCode": "en"}]}, "boundingBox": {"vertices": [{"x": 449, "y": 98}, {"x": 457, "y": 96}, {"x": 459, "y": 107}, {"x": 451, "y": 109}]}, "text": "J"}, {"property": {"detectedLanguages": [{"languageCode": "en"}]}, "boundingBox": {"vertices": [{"x": 458, "y": 96}, {"x": 461, "y": 95}, {"x": 463, "y": 106}, {"x": 460, "y": 107}]}, "text": "E"}, {"property": {"detectedLanguages": [{"languageCode": "en"}]}, "boundingBox": {"vertices": [{"x": 462, "y": 95}, {"x": 467, "y": 94}, {"x": 469, "y": 105}, {"x": 464, "y": 106}]}, "text": "W"}, {"property": {"detectedLanguages": [{"languageCode": "en"}]}, "boundingBox": {"vertices": [{"x": 468, "y": 94}, {"x": 471, "y": 93}, {"x": 473, "y": 104}, {"x": 470, "y": 105}]}, "text": "E"}, {"property": {"detectedLanguages": [{"languageCode": "en"}]}, "boundingBox": {"vertices": [{"x": 472, "y": 93}, {"x": 475, "y": 92}, {"x": 477, "y": 103}, {"x": 474, "y": 104}]}, "text": "L"}, {"property": {"detectedLanguages": [{"languageCode": "en"}]}, "boundingBox": {"vertices": [{"x": 475, "y": 92}, {"x": 478, "y": 91}, {"x": 480, "y": 102}, {"x": 477, "y": 103}]}, "text": "R"}, {"property": {"detectedLanguages": [{"languageCode": "en"}], "detectedBreak": {"type": "EOL_SURE_SPACE"}}, "boundingBox": {"vertices": [{"x": 479, "y": 92}, {"x": 484, "y": 91}, {"x": 486, "y": 102}, {"x": 481, "y": 103}]}, "text": "Y"}]}, {"boundingBox": {"vertices": [{"x": 461, "y": 110}, {"x": 474, "y": 108}, {"x": 475, "y": 115}, {"x": 462, "y": 117}]}, "symbols": [{"boundingBox": {"vertices": [{"x": 461, "y": 110}, {"x": 466, "y": 109}, {"x": 467, "y": 116}, {"x": 462, "y": 117}]}, "text": "C"}, {"boundingBox": {"vertices": [{"x": 467, "y": 109}, {"x": 468, "y": 109}, {"x": 469, "y": 116}, {"x": 468, "y": 116}]}, "text": "A"}, {"boundingBox": {"vertices": [{"x": 469, "y": 109}, {"x": 472, "y": 108}, {"x": 473, "y": 115}, {"x": 470, "y": 116}]}, "text": "S"}, {"property": {"detectedBreak": {"type": "LINE_BREAK"}}, "boundingBox": {"vertices": [{"x": 473, "y": 108}, {"x": 474, "y": 108}, {"x": 475, "y": 115}, {"x": 474, "y": 115}]}, "text": "A"}]}]}], "blockType": "TEXT"}, {"property": {"detectedLanguages": [{"languageCode": "pt", "confidence": 0.7}]}, "boundingBox": {"vertices": [{"x": 456, "y": 120}, {"x": 481, "y": 116}, {"x": 484, "y": 135}, {"x": 459, "y": 139}]}, "paragraphs": [{"property": {"detectedLanguages": [{"languageCode": "pt", "confidence": 0.7}]}, "boundingBox": {"vertices": [{"x": 456, "y": 120}, {"x": 481, "y": 116}, {"x": 484, "y": 135}, {"x": 459, "y": 139}]}, "words": [{"property": {"detectedLanguages": [{"languageCode": "pt"}]}, "boundingBox": {"vertices": [{"x": 456, "y": 120}, {"x": 461, "y": 119}, {"x": 463, "y": 129}, {"x": 458, "y": 130}]}, "symbols": [{"property": {"detectedLanguages": [{"languageCode": "pt"}], "detectedBreak": {"type": "SPACE"}}, "boundingBox": {"vertices": [{"x": 456, "y": 120}, {"x": 461, "y": 119}, {"x": 463, "y": 129}, {"x": 458, "y": 130}]}, "text": "E"}]}, {"property": {"detectedLanguages": [{"languageCode": "pt"}]}, "boundingBox": {"vertices": [{"x": 463, "y": 119}, {"x": 481, "y": 116}, {"x": 483, "y": 127}, {"x": 465, "y": 130}]}, "symbols": [{"property": {"detectedLanguages": [{"languageCode": "pt"}]}, "boundingBox": {"vertices": [{"x": 463, "y": 120}, {"x": 465, "y": 120}, {"x": 467, "y": 130}, {"x": 465, "y": 130}]}, "text": "E"}, {"property": {"detectedLanguages": [{"languageCode": "pt"}]}, "boundingBox": {"vertices": [{"x": 466, "y": 119}, {"x": 469, "y": 119}, {"x": 471, "y": 128}, {"x": 468, "y": 129}]}, "text": "M"}, {"property": {"detectedLanguages": [{"languageCode": "pt"}]}, "boundingBox": {"vertices": [{"x": 470, "y": 118}, {"x": 472, "y": 118}, {"x": 474, "y": 128}, {"x": 472, "y": 128}]}, "text": "P"}, {"property": {"detectedLanguages": [{"languageCode": "pt"}]}, "boundingBox": {"vertices": [{"x": 473, "y": 118}, {"x": 474, "y": 118}, {"x": 476, "y": 128}, {"x": 475, "y": 128}]}, "text": "E"}, {"property": {"detectedLanguages": [{"languageCode": "pt"}]}, "boundingBox": {"vertices": [{"x": 475, "y": 118}, {"x": 480, "y": 117}, {"x": 482, "y": 127}, {"x": 477, "y": 128}]}, "text": "N"}, {"property": {"detectedLanguages": [{"languageCode": "pt"}], "detectedBreak": {"type": "EOL_SURE_SPACE"}}, "boundingBox": {"vertices": [{"x": 481, "y": 117}, {"x": 481, "y": 117}, {"x": 483, "y": 127}, {"x": 483, "y": 127}]}, "text": "O"}]}, {"boundingBox": {"vertices": [{"x": 462, "y": 130}, {"x": 475, "y": 129}, {"x": 476, "y": 136}, {"x": 463, "y": 137}]}, "symbols": [{"boundingBox": {"vertices": [{"x": 462, "y": 131}, {"x": 467, "y": 130}, {"x": 468, "y": 136}, {"x": 463, "y": 137}]}, "text": "7"}, {"boundingBox": {"vertices": [{"x": 468, "y": 130}, {"x": 471, "y": 130}, {"x": 472, "y": 136}, {"x": 469, "y": 136}]}, "text": "0"}, {"property": {"detectedBreak": {"type": "LINE_BREAK"}}, "boundingBox": {"vertices": [{"x": 472, "y": 129}, {"x": 475, "y": 129}, {"x": 476, "y": 135}, {"x": 473, "y": 135}]}, "text": "9"}]}]}], "blockType": "TEXT"}, {"property": {"detectedLanguages": [{"languageCode": "es", "confidence": 0.5}, {"languageCode": "en", "confidence": 0.26}, {"languageCode": "pt", "confidence": 0.24}]}, "boundingBox": {"vertices": [{"x": -3, "y": 178}, {"x": 66, "y": 174}, {"x": 70, "y": 249}, {"x": 1, "y": 253}]}, "paragraphs": [{"property": {"detectedLanguages": [{"languageCode": "es", "confidence": 0.5}, {"languageCode": "en", "confidence": 0.26}, {"languageCode": "pt", "confidence": 0.24}]}, "boundingBox": {"vertices": [{"x": -3, "y": 178}, {"x": 66, "y": 174}, {"x": 70, "y": 249}, {"x": 1, "y": 253}]}, "words": [{"property": {"detectedLanguages": [{"languageCode": "en"}]}, "boundingBox": {"vertices": [{"x": 13, "y": 182}, {"x": 61, "y": 174}, {"x": 64, "y": 189}, {"x": 15, "y": 197}]}, "symbols": [{"property": {"detectedLanguages": [{"languageCode": "en"}]}, "boundingBox": {"vertices": [{"x": 13, "y": 182}, {"x": 22, "y": 181}, {"x": 24, "y": 195}, {"x": 15, "y": 197}]}, "text": "T"}, {"property": {"detectedLanguages": [{"languageCode": "en"}]}, "boundingBox": {"vertices": [{"x": 23, "y": 180}, {"x": 34, "y": 178}, {"x": 36, "y": 193}, {"x": 25, "y": 195}]}, "text": "O"}, {"property": {"detectedLanguages": [{"languageCode": "en"}]}, "boundingBox": {"vertices": [{"x": 35, "y": 179}, {"x": 40, "y": 178}, {"x": 42, "y": 193}, {"x": 37, "y": 194}]}, "text": "O"}, {"property": {"detectedLanguages": [{"languageCode": "en"}]}, "boundingBox": {"vertices": [{"x": 41, "y": 178}, {"x": 49, "y": 177}, {"x": 51, "y": 192}, {"x": 43, "y": 193}]}, "text": "U"}, {"property": {"detectedLanguages": [{"languageCode": "en"}], "detectedBreak": {"type": "EOL_SURE_SPACE"}}, "boundingBox": {"vertices": [{"x": 50, "y": 176}, {"x": 62, "y": 174}, {"x": 64, "y": 189}, {"x": 52, "y": 191}]}, "text": "S"}]}, {"property": {"detectedLanguages": [{"languageCode": "es"}]}, "boundingBox": {"vertices": [{"x": 1, "y": 199}, {"x": 11, "y": 198}, {"x": 12, "y": 211}, {"x": 3, "y": 212}]}, "symbols": [{"property": {"detectedLanguages": [{"languageCode": "es"}]}, "boundingBox": {"vertices": [{"x": 1, "y": 199}, {"x": 6, "y": 198}, {"x": 7, "y": 211}, {"x": 3, "y": 212}]}, "text": "U"}, {"property": {"detectedLanguages": [{"languageCode": "es"}], "detectedBreak": {"type": "SPACE"}}, "boundingBox": {"vertices": [{"x": 7, "y": 198}, {"x": 11, "y": 198}, {"x": 12, "y": 210}, {"x": 9, "y": 211}]}, "text": "S"}]}, {"property": {"detectedLanguages": [{"languageCode": "es"}]}, "boundingBox": {"vertices": [{"x": 12, "y": 197}, {"x": 66, "y": 191}, {"x": 67, "y": 205}, {"x": 14, "y": 211}]}, "symbols": [{"property": {"detectedLanguages": [{"languageCode": "es"}]}, "boundingBox": {"vertices": [{"x": 12, "y": 197}, {"x": 20, "y": 196}, {"x": 21, "y": 209}, {"x": 14, "y": 210}]}, "text": "J"}, {"property": {"detectedLanguages": [{"languageCode": "es"}]}, "boundingBox": {"vertices": [{"x": 21, "y": 196}, {"x": 25, "y": 196}, {"x": 26, "y": 208}, {"x": 23, "y": 209}]}, "text": "U"}, {"property": {"detectedLanguages": [{"languageCode": "es"}]}, "boundingBox": {"vertices": [{"x": 26, "y": 196}, {"x": 29, "y": 196}, {"x": 31, "y": 209}, {"x": 28, "y": 209}]}, "text": "Z"}, {"property": {"detectedLanguages": [{"languageCode": "es"}]}, "boundingBox": {"vertices": [{"x": 30, "y": 195}, {"x": 36, "y": 194}, {"x": 37, "y": 207}, {"x": 32, "y": 208}]}, "text": "G"}, {"property": {"detectedLanguages": [{"languageCode": "es"}]}, "boundingBox": {"vertices": [{"x": 36, "y": 194}, {"x": 40, "y": 194}, {"x": 41, "y": 206}, {"x": 38, "y": 207}]}, "text": "A"}, {"property": {"detectedLanguages": [{"languageCode": "es"}]}, "boundingBox": {"vertices": [{"x": 42, "y": 194}, {"x": 50, "y": 193}, {"x": 51, "y": 206}, {"x": 44, "y": 207}]}, "text": "D"}, {"property": {"detectedLanguages": [{"languageCode": "es"}]}, "boundingBox": {"vertices": [{"x": 51, "y": 193}, {"x": 57, "y": 192}, {"x": 58, "y": 205}, {"x": 53, "y": 206}]}, "text": "O"}, {"property": {"detectedLanguages": [{"languageCode": "es"}], "detectedBreak": {"type": "EOL_SURE_SPACE"}}, "boundingBox": {"vertices": [{"x": 58, "y": 192}, {"x": 66, "y": 191}, {"x": 67, "y": 204}, {"x": 60, "y": 205}]}, "text": "S"}]}, {"property": {"detectedLanguages": [{"languageCode": "es"}]}, "boundingBox": {"vertices": [{"x": 1, "y": 211}, {"x": 13, "y": 210}, {"x": 14, "y": 224}, {"x": 2, "y": 225}]}, "symbols": [{"property": {"detectedLanguages": [{"languageCode": "es"}]}, "boundingBox": {"vertices": [{"x": 1, "y": 212}, {"x": 6, "y": 212}, {"x": 7, "y": 225}, {"x": 2, "y": 225}]}, "text": "E"}, {"property": {"detectedLanguages": [{"languageCode": "es"}]}, "boundingBox": {"vertices": [{"x": 7, "y": 211}, {"x": 8, "y": 211}, {"x": 9, "y": 224}, {"x": 8, "y": 224}]}, "text": "N"}, {"property": {"detectedLanguages": [{"languageCode": "es"}], "detectedBreak": {"type": "SPACE"}}, "boundingBox": {"vertices": [{"x": 9, "y": 211}, {"x": 13, "y": 211}, {"x": 14, "y": 224}, {"x": 10, "y": 224}]}, "text": "D"}]}, {"property": {"detectedLanguages": [{"languageCode": "es"}]}, "boundingBox": {"vertices": [{"x": 13, "y": 213}, {"x": 23, "y": 212}, {"x": 24, "y": 220}, {"x": 14, "y": 221}]}, "symbols": [{"property": {"detectedLanguages": [{"languageCode": "es"}]}, "boundingBox": {"vertices": [{"x": 13, "y": 213}, {"x": 20, "y": 213}, {"x": 21, "y": 220}, {"x": 14, "y": 221}]}, "text": "D"}, {"property": {"detectedLanguages": [{"languageCode": "es"}], "detectedBreak": {"type": "SPACE"}}, "boundingBox": {"vertices": [{"x": 21, "y": 212}, {"x": 23, "y": 212}, {"x": 24, "y": 220}, {"x": 22, "y": 220}]}, "text": "E"}]}, {"property": {"detectedLanguages": [{"languageCode": "es"}]}, "boundingBox": {"vertices": [{"x": 25, "y": 210}, {"x": 65, "y": 207}, {"x": 66, "y": 220}, {"x": 26, "y": 223}]}, "symbols": [{"property": {"detectedLanguages": [{"languageCode": "es"}]}, "boundingBox": {"vertices": [{"x": 25, "y": 210}, {"x": 36, "y": 209}, {"x": 37, "y": 222}, {"x": 26, "y": 223}]}, "text": "C"}, {"property": {"detectedLanguages": [{"languageCode": "es"}]}, "boundingBox": {"vertices": [{"x": 37, "y": 209}, {"x": 39, "y": 209}, {"x": 40, "y": 222}, {"x": 38, "y": 222}]}, "text": "R"}, {"property": {"detectedLanguages": [{"languageCode": "es"}]}, "boundingBox": {"vertices": [{"x": 40, "y": 209}, {"x": 43, "y": 209}, {"x": 44, "y": 222}, {"x": 41, "y": 222}]}, "text": "I"}, {"property": {"detectedLanguages": [{"languageCode": "es"}]}, "boundingBox": {"vertices": [{"x": 44, "y": 209}, {"x": 50, "y": 209}, {"x": 51, "y": 222}, {"x": 45, "y": 222}]}, "text": "S"}, {"property": {"detectedLanguages": [{"languageCode": "es"}]}, "boundingBox": {"vertices": [{"x": 51, "y": 208}, {"x": 55, "y": 208}, {"x": 56, "y": 221}, {"x": 52, "y": 221}]}, "text": "T"}, {"property": {"detectedLanguages": [{"languageCode": "es"}], "detectedBreak": {"type": "EOL_SURE_SPACE"}}, "boundingBox": {"vertices": [{"x": 56, "y": 208}, {"x": 65, "y": 207}, {"x": 66, "y": 220}, {"x": 57, "y": 221}]}, "text": "O"}]}, {"property": {"detectedLanguages": [{"languageCode": "pt"}]}, "boundingBox": {"vertices": [{"x": 1, "y": 223}, {"x": 25, "y": 223}, {"x": 25, "y": 236}, {"x": 1, "y": 236}]}, "symbols": [{"property": {"detectedLanguages": [{"languageCode": "pt"}]}, "boundingBox": {"vertices": [{"x": 1, "y": 223}, {"x": 6, "y": 223}, {"x": 6, "y": 236}, {"x": 1, "y": 236}]}, "text": "S"}, {"property": {"detectedLanguages": [{"languageCode": "pt"}]}, "boundingBox": {"vertices": [{"x": 7, "y": 223}, {"x": 11, "y": 223}, {"x": 11, "y": 236}, {"x": 7, "y": 236}]}, "text": "T"}, {"property": {"detectedLanguages": [{"languageCode": "pt"}]}, "boundingBox": {"vertices": [{"x": 12, "y": 223}, {"x": 15, "y": 223}, {"x": 15, "y": 236}, {"x": 12, "y": 236}]}, "text": "R"}, {"property": {"detectedLanguages": [{"languageCode": "pt"}]}, "boundingBox": {"vertices": [{"x": 16, "y": 223}, {"x": 20, "y": 223}, {"x": 20, "y": 236}, {"x": 16, "y": 236}]}, "text": "A"}, {"property": {"detectedLanguages": [{"languageCode": "pt"}], "detectedBreak": {"type": "SPACE"}}, "boundingBox": {"vertices": [{"x": 21, "y": 223}, {"x": 25, "y": 223}, {"x": 25, "y": 236}, {"x": 21, "y": 236}]}, "text": "S"}]}, {"property": {"detectedLanguages": [{"languageCode": "pt"}]}, "boundingBox": {"vertices": [{"x": 27, "y": 222}, {"x": 60, "y": 222}, {"x": 60, "y": 236}, {"x": 27, "y": 236}]}, "symbols": [{"property": {"detectedLanguages": [{"languageCode": "pt"}]}, "boundingBox": {"vertices": [{"x": 27, "y": 223}, {"x": 36, "y": 223}, {"x": 36, "y": 236}, {"x": 27, "y": 236}]}, "text": "O"}, {"property": {"detectedLanguages": [{"languageCode": "pt"}]}, "boundingBox": {"vertices": [{"x": 37, "y": 223}, {"x": 43, "y": 223}, {"x": 43, "y": 236}, {"x": 37, "y": 236}]}, "text": "B"}, {"property": {"detectedLanguages": [{"languageCode": "pt"}]}, "boundingBox": {"vertices": [{"x": 44, "y": 222}, {"x": 50, "y": 222}, {"x": 50, "y": 235}, {"x": 44, "y": 235}]}, "text": "R"}, {"property": {"detectedLanguages": [{"languageCode": "pt"}]}, "boundingBox": {"vertices": [{"x": 51, "y": 222}, {"x": 55, "y": 222}, {"x": 55, "y": 235}, {"x": 51, "y": 235}]}, "text": "A"}, {"property": {"detectedLanguages": [{"languageCode": "pt"}], "detectedBreak": {"type": "EOL_SURE_SPACE"}}, "boundingBox": {"vertices": [{"x": 56, "y": 222}, {"x": 60, "y": 222}, {"x": 60, "y": 235}, {"x": 56, "y": 235}]}, "text": "S"}]}, {"property": {"detectedLanguages": [{"languageCode": "en"}]}, "boundingBox": {"vertices": [{"x": 20, "y": 238}, {"x": 40, "y": 239}, {"x": 40, "y": 250}, {"x": 20, "y": 249}]}, "symbols": [{"property": {"detectedLanguages": [{"languageCode": "en"}]}, "boundingBox": {"vertices": [{"x": 20, "y": 239}, {"x": 21, "y": 239}, {"x": 21, "y": 243}, {"x": 20, "y": 243}]}, "text": "S"}, {"property": {"detectedLanguages": [{"languageCode": "en"}]}, "boundingBox": {"vertices": [{"x": 24, "y": 241}, {"x": 25, "y": 241}, {"x": 25, "y": 245}, {"x": 24, "y": 245}]}, "text": "M"}, {"property": {"detectedLanguages": [{"languageCode": "en"}]}, "boundingBox": {"vertices": [{"x": 29, "y": 238}, {"x": 32, "y": 238}, {"x": 32, "y": 245}, {"x": 29, "y": 245}]}, "text": "A"}, {"property": {"detectedLanguages": [{"languageCode": "en"}], "detectedBreak": {"type": "SPACE"}}, "boundingBox": {"vertices": [{"x": 34, "y": 239}, {"x": 40, "y": 239}, {"x": 40, "y": 249}, {"x": 34, "y": 249}]}, "text": "I"}]}, {"property": {"detectedLanguages": [{"languageCode": "en"}]}, "boundingBox": {"vertices": [{"x": 44, "y": 238}, {"x": 56, "y": 238}, {"x": 56, "y": 249}, {"x": 44, "y": 249}]}, "symbols": [{"property": {"detectedLanguages": [{"languageCode": "en"}]}, "boundingBox": {"vertices": [{"x": 44, "y": 238}, {"x": 52, "y": 238}, {"x": 52, "y": 249}, {"x": 44, "y": 249}]}, "text": "A"}, {"property": {"detectedLanguages": [{"languageCode": "en"}], "detectedBreak": {"type": "LINE_BREAK"}}, "boundingBox": {"vertices": [{"x": 53, "y": 238}, {"x": 56, "y": 238}, {"x": 56, "y": 249}, {"x": 53, "y": 249}]}, "text": "S"}]}]}], "blockType": "TEXT"}, {"property": {"detectedLanguages": [{"languageCode": "en", "confidence": 0.5}, {"languageCode": "es", "confidence": 0.5}]}, "boundingBox": {"vertices": [{"x": 354, "y": 153}, {"x": 464, "y": 165}, {"x": 460, "y": 202}, {"x": 350, "y": 190}]}, "paragraphs": [{"property": {"detectedLanguages": [{"languageCode": "en", "confidence": 0.5}, {"languageCode": "es", "confidence": 0.5}]}, "boundingBox": {"vertices": [{"x": 354, "y": 153}, {"x": 464, "y": 165}, {"x": 460, "y": 202}, {"x": 350, "y": 190}]}, "words": [{"property": {"detectedLanguages": [{"languageCode": "en"}]}, "boundingBox": {"vertices": [{"x": 354, "y": 153}, {"x": 407, "y": 160}, {"x": 404, "y": 177}, {"x": 352, "y": 170}]}, "symbols": [{"property": {"detectedLanguages": [{"languageCode": "en"}]}, "boundingBox": {"vertices": [{"x": 354, "y": 153}, {"x": 373, "y": 155}, {"x": 371, "y": 172}, {"x": 352, "y": 170}]}, "text": "M"}, {"property": {"detectedLanguages": [{"languageCode": "en"}]}, "boundingBox": {"vertices": [{"x": 374, "y": 156}, {"x": 389, "y": 158}, {"x": 387, "y": 175}, {"x": 372, "y": 173}]}, "text": "O"}, {"property": {"detectedLanguages": [{"languageCode": "en"}]}, "boundingBox": {"vertices": [{"x": 390, "y": 158}, {"x": 392, "y": 158}, {"x": 390, "y": 175}, {"x": 388, "y": 175}]}, "text": "N"}, {"property": {"detectedLanguages": [{"languageCode": "en"}]}, "boundingBox": {"vertices": [{"x": 393, "y": 158}, {"x": 398, "y": 159}, {"x": 396, "y": 176}, {"x": 391, "y": 175}]}, "text": "E"}, {"property": {"detectedLanguages": [{"languageCode": "en"}], "detectedBreak": {"type": "SPACE"}}, "boundingBox": {"vertices": [{"x": 398, "y": 159}, {"x": 407, "y": 160}, {"x": 405, "y": 177}, {"x": 396, "y": 176}]}, "text": "Y"}]}, {"property": {"detectedLanguages": [{"languageCode": "en"}]}, "boundingBox": {"vertices": [{"x": 414, "y": 162}, {"x": 429, "y": 164}, {"x": 427, "y": 178}, {"x": 412, "y": 176}]}, "symbols": [{"property": {"detectedLanguages": [{"languageCode": "en"}]}, "boundingBox": {"vertices": [{"x": 414, "y": 162}, {"x": 420, "y": 163}, {"x": 418, "y": 177}, {"x": 412, "y": 176}]}, "text": "T"}, {"property": {"detectedLanguages": [{"languageCode": "en"}], "detectedBreak": {"type": "SPACE"}}, "boundingBox": {"vertices": [{"x": 422, "y": 163}, {"x": 429, "y": 164}, {"x": 427, "y": 178}, {"x": 420, "y": 177}]}, "text": "O"}]}, {"property": {"detectedLanguages": [{"languageCode": "en"}]}, "boundingBox": {"vertices": [{"x": 435, "y": 163}, {"x": 464, "y": 167}, {"x": 461, "y": 185}, {"x": 433, "y": 181}]}, "symbols": [{"property": {"detectedLanguages": [{"languageCode": "en"}]}, "boundingBox": {"vertices": [{"x": 435, "y": 163}, {"x": 442, "y": 164}, {"x": 440, "y": 182}, {"x": 433, "y": 181}]}, "text": "L"}, {"property": {"detectedLanguages": [{"languageCode": "en"}]}, "boundingBox": {"vertices": [{"x": 443, "y": 164}, {"x": 448, "y": 165}, {"x": 446, "y": 183}, {"x": 441, "y": 182}]}, "text": "O"}, {"property": {"detectedLanguages": [{"languageCode": "en"}]}, "boundingBox": {"vertices": [{"x": 449, "y": 165}, {"x": 458, "y": 166}, {"x": 456, "y": 184}, {"x": 447, "y": 183}]}, "text": "A"}, {"property": {"detectedLanguages": [{"languageCode": "en"}], "detectedBreak": {"type": "EOL_SURE_SPACE"}}, "boundingBox": {"vertices": [{"x": 459, "y": 166}, {"x": 464, "y": 167}, {"x": 462, "y": 185}, {"x": 457, "y": 184}]}, "text": "N"}]}, {"property": {"detectedLanguages": [{"languageCode": "es"}]}, "boundingBox": {"vertices": [{"x": 365, "y": 177}, {"x": 396, "y": 180}, {"x": 395, "y": 194}, {"x": 364, "y": 191}]}, "symbols": [{"property": {"detectedLanguages": [{"languageCode": "es"}]}, "boundingBox": {"vertices": [{"x": 365, "y": 178}, {"x": 371, "y": 179}, {"x": 371, "y": 183}, {"x": 365, "y": 182}]}, "text": "A"}, {"property": {"detectedLanguages": [{"languageCode": "es"}]}, "boundingBox": {"vertices": [{"x": 374, "y": 178}, {"x": 387, "y": 179}, {"x": 386, "y": 193}, {"x": 373, "y": 192}]}, "text": "S"}, {"property": {"detectedLanguages": [{"languageCode": "es"}], "detectedBreak": {"type": "SPACE"}}, "boundingBox": {"vertices": [{"x": 389, "y": 180}, {"x": 396, "y": 181}, {"x": 395, "y": 194}, {"x": 388, "y": 193}]}, "text": "A"}]}, {"property": {"detectedLanguages": [{"languageCode": "es"}]}, "boundingBox": {"vertices": [{"x": 400, "y": 182}, {"x": 415, "y": 183}, {"x": 414, "y": 195}, {"x": 399, "y": 194}]}, "symbols": [{"property": {"detectedLanguages": [{"languageCode": "es"}]}, "boundingBox": {"vertices": [{"x": 400, "y": 182}, {"x": 410, "y": 183}, {"x": 409, "y": 195}, {"x": 399, "y": 194}]}, "text": "D"}, {"property": {"detectedLanguages": [{"languageCode": "es"}], "detectedBreak": {"type": "SPACE"}}, "boundingBox": {"vertices": [{"x": 411, "y": 183}, {"x": 415, "y": 183}, {"x": 414, "y": 195}, {"x": 410, "y": 195}]}, "text": "E"}]}, {"property": {"detectedLanguages": [{"languageCode": "es"}]}, "boundingBox": {"vertices": [{"x": 419, "y": 180}, {"x": 460, "y": 184}, {"x": 458, "y": 200}, {"x": 418, "y": 196}]}, "symbols": [{"property": {"detectedLanguages": [{"languageCode": "es"}]}, "boundingBox": {"vertices": [{"x": 419, "y": 180}, {"x": 425, "y": 181}, {"x": 424, "y": 195}, {"x": 418, "y": 195}]}, "text": "E"}, {"property": {"detectedLanguages": [{"languageCode": "es"}]}, "boundingBox": {"vertices": [{"x": 426, "y": 181}, {"x": 434, "y": 182}, {"x": 433, "y": 197}, {"x": 425, "y": 196}]}, "text": "M"}, {"property": {"detectedLanguages": [{"languageCode": "es"}]}, "boundingBox": {"vertices": [{"x": 435, "y": 182}, {"x": 440, "y": 182}, {"x": 439, "y": 197}, {"x": 434, "y": 197}]}, "text": "P"}, {"property": {"detectedLanguages": [{"languageCode": "es"}]}, "boundingBox": {"vertices": [{"x": 441, "y": 182}, {"x": 446, "y": 182}, {"x": 445, "y": 197}, {"x": 440, "y": 197}]}, "text": "E"}, {"property": {"detectedLanguages": [{"languageCode": "es"}]}, "boundingBox": {"vertices": [{"x": 447, "y": 183}, {"x": 455, "y": 184}, {"x": 454, "y": 199}, {"x": 446, "y": 198}]}, "text": "\u00d1"}, {"property": {"detectedLanguages": [{"languageCode": "es"}], "detectedBreak": {"type": "LINE_BREAK"}}, "boundingBox": {"vertices": [{"x": 456, "y": 184}, {"x": 460, "y": 184}, {"x": 459, "y": 199}, {"x": 455, "y": 199}]}, "text": "O"}]}]}], "blockType": "TEXT"}, {"boundingBox": {"vertices": [{"x": 481, "y": 173}, {"x": 499, "y": 174}, {"x": 498, "y": 182}, {"x": 480, "y": 181}]}, "paragraphs": [{"boundingBox": {"vertices": [{"x": 481, "y": 173}, {"x": 499, "y": 174}, {"x": 498, "y": 182}, {"x": 480, "y": 181}]}, "words": [{"boundingBox": {"vertices": [{"x": 481, "y": 173}, {"x": 499, "y": 174}, {"x": 498, "y": 182}, {"x": 480, "y": 181}]}, "symbols": [{"boundingBox": {"vertices": [{"x": 481, "y": 173}, {"x": 490, "y": 174}, {"x": 489, "y": 182}, {"x": 480, "y": 181}]}, "text": "U"}, {"boundingBox": {"vertices": [{"x": 491, "y": 174}, {"x": 492, "y": 174}, {"x": 491, "y": 182}, {"x": 490, "y": 182}]}, "text": "N"}, {"boundingBox": {"vertices": [{"x": 493, "y": 174}, {"x": 495, "y": 174}, {"x": 494, "y": 182}, {"x": 492, "y": 182}]}, "text": "I"}, {"property": {"detectedBreak": {"type": "LINE_BREAK"}}, "boundingBox": {"vertices": [{"x": 496, "y": 174}, {"x": 499, "y": 174}, {"x": 498, "y": 182}, {"x": 495, "y": 182}]}, "text": "O"}]}]}], "blockType": "TEXT"}, {"boundingBox": {"vertices": [{"x": 486, "y": 188}, {"x": 500, "y": 189}, {"x": 499, "y": 205}, {"x": 485, "y": 204}]}, "paragraphs": [{"boundingBox": {"vertices": [{"x": 486, "y": 188}, {"x": 500, "y": 189}, {"x": 499, "y": 205}, {"x": 485, "y": 204}]}, "words": [{"boundingBox": {"vertices": [{"x": 491, "y": 188}, {"x": 499, "y": 189}, {"x": 498, "y": 197}, {"x": 490, "y": 196}]}, "symbols": [{"boundingBox": {"vertices": [{"x": 491, "y": 188}, {"x": 496, "y": 188}, {"x": 496, "y": 195}, {"x": 491, "y": 195}]}, "text": "J"}, {"property": {"detectedBreak": {"type": "EOL_SURE_SPACE"}}, "boundingBox": {"vertices": [{"x": 497, "y": 189}, {"x": 499, "y": 189}, {"x": 499, "y": 196}, {"x": 497, "y": 196}]}, "text": "E"}]}, {"boundingBox": {"vertices": [{"x": 485, "y": 197}, {"x": 499, "y": 198}, {"x": 499, "y": 205}, {"x": 485, "y": 204}]}, "symbols": [{"boundingBox": {"vertices": [{"x": 485, "y": 197}, {"x": 495, "y": 198}, {"x": 495, "y": 205}, {"x": 485, "y": 204}]}, "text": "G"}, {"boundingBox": {"vertices": [{"x": 496, "y": 198}, {"x": 496, "y": 198}, {"x": 496, "y": 205}, {"x": 496, "y": 205}]}, "text": "U"}, {"property": {"detectedBreak": {"type": "LINE_BREAK"}}, "boundingBox": {"vertices": [{"x": 497, "y": 198}, {"x": 499, "y": 198}, {"x": 499, "y": 205}, {"x": 497, "y": 205}]}, "text": "N"}]}]}], "blockType": "TEXT"}, {"boundingBox": {"vertices": [{"x": 240, "y": 202}, {"x": 251, "y": 202}, {"x": 251, "y": 207}, {"x": 240, "y": 207}]}, "paragraphs": [{"boundingBox": {"vertices": [{"x": 240, "y": 202}, {"x": 251, "y": 202}, {"x": 251, "y": 207}, {"x": 240, "y": 207}]}, "words": [{"boundingBox": {"vertices": [{"x": 240, "y": 202}, {"x": 251, "y": 202}, {"x": 251, "y": 207}, {"x": 240, "y": 207}]}, "symbols": [{"boundingBox": {"vertices": [{"x": 240, "y": 202}, {"x": 243, "y": 202}, {"x": 243, "y": 207}, {"x": 240, "y": 207}]}, "text": "7"}, {"boundingBox": {"vertices": [{"x": 246, "y": 202}, {"x": 247, "y": 202}, {"x": 247, "y": 207}, {"x": 246, "y": 207}]}, "text": "1"}, {"property": {"detectedBreak": {"type": "LINE_BREAK"}}, "boundingBox": {"vertices": [{"x": 250, "y": 203}, {"x": 251, "y": 203}, {"x": 251, "y": 207}, {"x": 250, "y": 207}]}, "text": "1"}]}]}], "blockType": "TEXT"}, {"property": {"detectedLanguages": [{"languageCode": "en", "confidence": 1.0}]}, "boundingBox": {"vertices": [{"x": 129, "y": 214}, {"x": 187, "y": 216}, {"x": 186, "y": 235}, {"x": 128, "y": 233}]}, "paragraphs": [{"property": {"detectedLanguages": [{"languageCode": "en", "confidence": 1.0}]}, "boundingBox": {"vertices": [{"x": 129, "y": 214}, {"x": 187, "y": 216}, {"x": 186, "y": 235}, {"x": 128, "y": 233}]}, "words": [{"property": {"detectedLanguages": [{"languageCode": "en"}]}, "boundingBox": {"vertices": [{"x": 129, "y": 214}, {"x": 187, "y": 216}, {"x": 186, "y": 235}, {"x": 128, "y": 233}]}, "symbols": [{"property": {"detectedLanguages": [{"languageCode": "en"}]}, "boundingBox": {"vertices": [{"x": 129, "y": 214}, {"x": 153, "y": 215}, {"x": 152, "y": 234}, {"x": 128, "y": 233}]}, "text": "J"}, {"property": {"detectedLanguages": [{"languageCode": "en"}]}, "boundingBox": {"vertices": [{"x": 154, "y": 215}, {"x": 163, "y": 215}, {"x": 162, "y": 234}, {"x": 153, "y": 234}]}, "text": "E"}, {"property": {"detectedLanguages": [{"languageCode": "en"}]}, "boundingBox": {"vertices": [{"x": 164, "y": 215}, {"x": 169, "y": 215}, {"x": 168, "y": 234}, {"x": 163, "y": 234}]}, "text": "S"}, {"property": {"detectedLanguages": [{"languageCode": "en"}]}, "boundingBox": {"vertices": [{"x": 170, "y": 216}, {"x": 179, "y": 216}, {"x": 178, "y": 235}, {"x": 169, "y": 235}]}, "text": "U"}, {"property": {"detectedLanguages": [{"languageCode": "en"}], "detectedBreak": {"type": "LINE_BREAK"}}, "boundingBox": {"vertices": [{"x": 180, "y": 216}, {"x": 187, "y": 216}, {"x": 186, "y": 235}, {"x": 179, "y": 235}]}, "text": "S"}]}]}], "blockType": "TEXT"}, {"property": {"detectedLanguages": [{"languageCode": "es", "confidence": 1.0}]}, "boundingBox": {"vertices": [{"x": 362, "y": 216}, {"x": 470, "y": 220}, {"x": 470, "y": 229}, {"x": 362, "y": 225}]}, "paragraphs": [{"property": {"detectedLanguages": [{"languageCode": "es", "confidence": 1.0}]}, "boundingBox": {"vertices": [{"x": 362, "y": 216}, {"x": 470, "y": 220}, {"x": 470, "y": 229}, {"x": 362, "y": 225}]}, "words": [{"property": {"detectedLanguages": [{"languageCode": "es"}]}, "boundingBox": {"vertices": [{"x": 362, "y": 216}, {"x": 470, "y": 220}, {"x": 470, "y": 229}, {"x": 362, "y": 225}]}, "symbols": [{"property": {"detectedLanguages": [{"languageCode": "es"}]}, "boundingBox": {"vertices": [{"x": 362, "y": 216}, {"x": 374, "y": 216}, {"x": 374, "y": 225}, {"x": 362, "y": 225}]}, "text": "E"}, {"property": {"detectedLanguages": [{"languageCode": "es"}]}, "boundingBox": {"vertices": [{"x": 375, "y": 216}, {"x": 382, "y": 216}, {"x": 382, "y": 225}, {"x": 375, "y": 225}]}, "text": "X"}, {"property": {"detectedLanguages": [{"languageCode": "es"}]}, "boundingBox": {"vertices": [{"x": 383, "y": 217}, {"x": 387, "y": 217}, {"x": 387, "y": 226}, {"x": 383, "y": 226}]}, "text": "C"}, {"property": {"detectedLanguages": [{"languageCode": "es"}]}, "boundingBox": {"vertices": [{"x": 388, "y": 217}, {"x": 391, "y": 217}, {"x": 391, "y": 226}, {"x": 388, "y": 226}]}, "text": "E"}, {"property": {"detectedLanguages": [{"languageCode": "es"}]}, "boundingBox": {"vertices": [{"x": 392, "y": 217}, {"x": 396, "y": 217}, {"x": 396, "y": 226}, {"x": 392, "y": 226}]}, "text": "L"}, {"property": {"detectedLanguages": [{"languageCode": "es"}]}, "boundingBox": {"vertices": [{"x": 397, "y": 217}, {"x": 400, "y": 217}, {"x": 400, "y": 226}, {"x": 397, "y": 226}]}, "text": "E"}, {"property": {"detectedLanguages": [{"languageCode": "es"}]}, "boundingBox": {"vertices": [{"x": 401, "y": 217}, {"x": 407, "y": 217}, {"x": 407, "y": 226}, {"x": 401, "y": 226}]}, "text": "N"}, {"property": {"detectedLanguages": [{"languageCode": "es"}]}, "boundingBox": {"vertices": [{"x": 408, "y": 218}, {"x": 413, "y": 218}, {"x": 413, "y": 227}, {"x": 408, "y": 227}]}, "text": "T"}, {"property": {"detectedLanguages": [{"languageCode": "es"}]}, "boundingBox": {"vertices": [{"x": 414, "y": 218}, {"x": 418, "y": 218}, {"x": 418, "y": 227}, {"x": 414, "y": 227}]}, "text": "E"}, {"property": {"detectedLanguages": [{"languageCode": "es"}]}, "boundingBox": {"vertices": [{"x": 419, "y": 218}, {"x": 422, "y": 218}, {"x": 422, "y": 227}, {"x": 419, "y": 227}]}, "text": "S"}, {"property": {"detectedLanguages": [{"languageCode": "es"}]}, "boundingBox": {"vertices": [{"x": 423, "y": 218}, {"x": 437, "y": 219}, {"x": 437, "y": 228}, {"x": 423, "y": 227}]}, "text": "P"}, {"property": {"detectedLanguages": [{"languageCode": "es"}]}, "boundingBox": {"vertices": [{"x": 438, "y": 219}, {"x": 440, "y": 219}, {"x": 440, "y": 228}, {"x": 438, "y": 228}]}, "text": "R"}, {"property": {"detectedLanguages": [{"languageCode": "es"}]}, "boundingBox": {"vertices": [{"x": 441, "y": 219}, {"x": 444, "y": 219}, {"x": 444, "y": 228}, {"x": 441, "y": 228}]}, "text": "E"}, {"property": {"detectedLanguages": [{"languageCode": "es"}]}, "boundingBox": {"vertices": [{"x": 445, "y": 219}, {"x": 448, "y": 219}, {"x": 448, "y": 228}, {"x": 445, "y": 228}]}, "text": "S"}, {"property": {"detectedLanguages": [{"languageCode": "es"}]}, "boundingBox": {"vertices": [{"x": 449, "y": 219}, {"x": 453, "y": 219}, {"x": 453, "y": 228}, {"x": 449, "y": 228}]}, "text": "T"}, {"property": {"detectedLanguages": [{"languageCode": "es"}]}, "boundingBox": {"vertices": [{"x": 454, "y": 220}, {"x": 457, "y": 220}, {"x": 457, "y": 229}, {"x": 454, "y": 229}]}, "text": "A"}, {"property": {"detectedLanguages": [{"languageCode": "es"}]}, "boundingBox": {"vertices": [{"x": 458, "y": 220}, {"x": 462, "y": 220}, {"x": 462, "y": 229}, {"x": 458, "y": 229}]}, "text": "M"}, {"property": {"detectedLanguages": [{"languageCode": "es"}], "detectedBreak": {"type": "LINE_BREAK"}}, "boundingBox": {"vertices": [{"x": 463, "y": 220}, {"x": 470, "y": 220}, {"x": 470, "y": 229}, {"x": 463, "y": 229}]}, "text": "S"}]}]}], "blockType": "TEXT"}, {"boundingBox": {"vertices": [{"x": 147, "y": 241}, {"x": 164, "y": 241}, {"x": 164, "y": 257}, {"x": 147, "y": 257}]}, "paragraphs": [{"boundingBox": {"vertices": [{"x": 147, "y": 241}, {"x": 164, "y": 241}, {"x": 164, "y": 257}, {"x": 147, "y": 257}]}, "words": [{"boundingBox": {"vertices": [{"x": 147, "y": 241}, {"x": 164, "y": 241}, {"x": 164, "y": 257}, {"x": 147, "y": 257}]}, "symbols": [{"boundingBox": {"vertices": [{"x": 147, "y": 241}, {"x": 162, "y": 241}, {"x": 162, "y": 257}, {"x": 147, "y": 257}]}, "text": "I"}, {"property": {"detectedBreak": {"type": "LINE_BREAK"}}, "boundingBox": {"vertices": [{"x": 163, "y": 241}, {"x": 164, "y": 241}, {"x": 164, "y": 257}, {"x": 163, "y": 257}]}, "text": "S"}]}]}], "blockType": "TEXT"}, {"property": {"detectedLanguages": [{"languageCode": "en", "confidence": 0.54}, {"languageCode": "fr", "confidence": 0.46}]}, "boundingBox": {"vertices": [{"x": 272, "y": 240}, {"x": 301, "y": 239}, {"x": 301, "y": 252}, {"x": 272, "y": 253}]}, "paragraphs": [{"property": {"detectedLanguages": [{"languageCode": "en", "confidence": 0.54}, {"languageCode": "fr", "confidence": 0.46}]}, "boundingBox": {"vertices": [{"x": 272, "y": 240}, {"x": 301, "y": 239}, {"x": 301, "y": 252}, {"x": 272, "y": 253}]}, "words": [{"property": {"detectedLanguages": [{"languageCode": "fr"}]}, "boundingBox": {"vertices": [{"x": 272, "y": 240}, {"x": 286, "y": 240}, {"x": 286, "y": 245}, {"x": 272, "y": 245}]}, "symbols": [{"property": {"detectedLanguages": [{"languageCode": "fr"}]}, "boundingBox": {"vertices": [{"x": 272, "y": 240}, {"x": 275, "y": 240}, {"x": 275, "y": 245}, {"x": 272, "y": 245}]}, "text": "\u00b7"}, {"property": {"detectedLanguages": [{"languageCode": "fr"}]}, "boundingBox": {"vertices": [{"x": 276, "y": 240}, {"x": 277, "y": 240}, {"x": 277, "y": 245}, {"x": 276, "y": 245}]}, "text": "F"}, {"property": {"detectedLanguages": [{"languageCode": "fr"}]}, "boundingBox": {"vertices": [{"x": 278, "y": 240}, {"x": 279, "y": 240}, {"x": 279, "y": 245}, {"x": 278, "y": 245}]}, "text": "A"}, {"property": {"detectedLanguages": [{"languageCode": "fr"}]}, "boundingBox": {"vertices": [{"x": 280, "y": 240}, {"x": 282, "y": 240}, {"x": 282, "y": 245}, {"x": 280, "y": 245}]}, "text": "N"}, {"property": {"detectedLanguages": [{"languageCode": "fr"}]}, "boundingBox": {"vertices": [{"x": 283, "y": 240}, {"x": 284, "y": 240}, {"x": 284, "y": 245}, {"x": 283, "y": 245}]}, "text": "E"}, {"property": {"detectedLanguages": [{"languageCode": "fr"}], "detectedBreak": {"type": "EOL_SURE_SPACE"}}, "boundingBox": {"vertices": [{"x": 285, "y": 240}, {"x": 286, "y": 240}, {"x": 286, "y": 245}, {"x": 285, "y": 245}]}, "text": "S"}]}, {"property": {"detectedLanguages": [{"languageCode": "en"}]}, "boundingBox": {"vertices": [{"x": 272, "y": 246}, {"x": 284, "y": 246}, {"x": 284, "y": 252}, {"x": 272, "y": 252}]}, "symbols": [{"property": {"detectedLanguages": [{"languageCode": "en"}]}, "boundingBox": {"vertices": [{"x": 272, "y": 247}, {"x": 279, "y": 247}, {"x": 279, "y": 252}, {"x": 272, "y": 252}]}, "text": "S"}, {"property": {"detectedLanguages": [{"languageCode": "en"}]}, "boundingBox": {"vertices": [{"x": 280, "y": 247}, {"x": 280, "y": 247}, {"x": 280, "y": 252}, {"x": 280, "y": 252}]}, "text": "L"}, {"property": {"detectedLanguages": [{"languageCode": "en"}]}, "boundingBox": {"vertices": [{"x": 281, "y": 247}, {"x": 283, "y": 247}, {"x": 283, "y": 252}, {"x": 281, "y": 252}]}, "text": "A"}, {"property": {"detectedLanguages": [{"languageCode": "en"}], "detectedBreak": {"type": "SPACE"}}, "boundingBox": {"vertices": [{"x": 284, "y": 246}, {"x": 284, "y": 246}, {"x": 284, "y": 251}, {"x": 284, "y": 251}]}, "text": "I"}]}, {"property": {"detectedLanguages": [{"languageCode": "en"}]}, "boundingBox": {"vertices": [{"x": 287, "y": 245}, {"x": 301, "y": 244}, {"x": 301, "y": 251}, {"x": 287, "y": 252}]}, "symbols": [{"property": {"detectedLanguages": [{"languageCode": "en"}]}, "boundingBox": {"vertices": [{"x": 287, "y": 245}, {"x": 291, "y": 245}, {"x": 291, "y": 252}, {"x": 287, "y": 252}]}, "text": "T"}, {"property": {"detectedLanguages": [{"languageCode": "en"}]}, "boundingBox": {"vertices": [{"x": 292, "y": 245}, {"x": 294, "y": 245}, {"x": 294, "y": 252}, {"x": 292, "y": 252}]}, "text": "O"}, {"property": {"detectedLanguages": [{"languageCode": "en"}], "detectedBreak": {"type": "LINE_BREAK"}}, "boundingBox": {"vertices": [{"x": 295, "y": 245}, {"x": 301, "y": 245}, {"x": 301, "y": 252}, {"x": 295, "y": 252}]}, "text": "P"}]}]}], "blockType": "TEXT"}, {"boundingBox": {"vertices": [{"x": 126, "y": 265}, {"x": 178, "y": 265}, {"x": 178, "y": 284}, {"x": 126, "y": 284}]}, "paragraphs": [{"boundingBox": {"vertices": [{"x": 126, "y": 265}, {"x": 178, "y": 265}, {"x": 178, "y": 284}, {"x": 126, "y": 284}]}, "words": [{"boundingBox": {"vertices": [{"x": 126, "y": 265}, {"x": 178, "y": 265}, {"x": 178, "y": 284}, {"x": 126, "y": 284}]}, "symbols": [{"boundingBox": {"vertices": [{"x": 126, "y": 265}, {"x": 151, "y": 265}, {"x": 151, "y": 284}, {"x": 126, "y": 284}]}, "text": "L"}, {"boundingBox": {"vertices": [{"x": 152, "y": 265}, {"x": 161, "y": 265}, {"x": 161, "y": 284}, {"x": 152, "y": 284}]}, "text": "O"}, {"boundingBox": {"vertices": [{"x": 162, "y": 265}, {"x": 168, "y": 265}, {"x": 168, "y": 284}, {"x": 162, "y": 284}]}, "text": "R"}, {"property": {"detectedBreak": {"type": "LINE_BREAK"}}, "boundingBox": {"vertices": [{"x": 169, "y": 265}, {"x": 178, "y": 265}, {"x": 178, "y": 284}, {"x": 169, "y": 284}]}, "text": "D"}]}]}], "blockType": "TEXT"}]}], "text": "MONEY\nLOAN\n-10-\nBARBER SALON\nDIAMOND\nJEWELRY\nCASA\nE EMPENO\n709\nTOOUS\nUS JUZGADOS\nEND DE CRISTO\nSTRAS OBRAS\nSMAI AS\nMONEY TO LOAN\nASA DE EMPE\u00d1O\nUNIO\nJE\nGUN\n711\nJESUS\nEXCELENTESPRESTAMS\nIS\n\u00b7FANES\nSLAI TOP\nLORD\n"}}